{
  "name": "Same Name",
  "answers": [
    {
      "answer": "A Chorus  Waiting Line",
      "numberOfWords": 4,
      "numberOfLetters": 18
    },
    {
      "answer": "African  Shrinking Violet",
      "numberOfWords": 3,
      "numberOfLetters": 22
    },
    {
      "answer": "African And Shrinking Violet",
      "numberOfWords": 4,
      "numberOfLetters": 25
    },
    {
      "answer": "Airport And Project Runway",
      "numberOfWords": 4,
      "numberOfLetters": 23
    },
    {
      "answer": "Alcatraz  Gilligans Island",
      "numberOfWords": 3,
      "numberOfLetters": 23
    },
    {
      "answer": "Alexander  George Hamilton",
      "numberOfWords": 3,
      "numberOfLetters": 23
    },
    {
      "answer": "Alexander And George Hamilton",
      "numberOfWords": 4,
      "numberOfLetters": 26
    },
    {
      "answer": "Alice  Coco Cooper",
      "numberOfWords": 3,
      "numberOfLetters": 15
    },
    {
      "answer": "Alicia  Car Keys",
      "numberOfWords": 3,
      "numberOfLetters": 13
    },
    {
      "answer": "Alien  Human Beings",
      "numberOfWords": 3,
      "numberOfLetters": 16
    },
    {
      "answer": "Alphabetical  Numerical Order",
      "numberOfWords": 3,
      "numberOfLetters": 26
    },
    {
      "answer": "Amazon River  Ganges River Dolphin",
      "numberOfWords": 5,
      "numberOfLetters": 29
    },
    {
      "answer": "Andrew  Dont Press Your Luck",
      "numberOfWords": 5,
      "numberOfLetters": 23
    },
    {
      "answer": "Ann  Chicken Curry",
      "numberOfWords": 3,
      "numberOfLetters": 15
    },
    {
      "answer": "Annie  Banquet Hall",
      "numberOfWords": 3,
      "numberOfLetters": 16
    },
    {
      "answer": "Ant  British Colony",
      "numberOfWords": 3,
      "numberOfLetters": 16
    },
    {
      "answer": "Antique  Voting Booth",
      "numberOfWords": 3,
      "numberOfLetters": 18
    },
    {
      "answer": "Appeals  Kings Court",
      "numberOfWords": 3,
      "numberOfLetters": 17
    },
    {
      "answer": "Artichoke  Artificial Heart",
      "numberOfWords": 3,
      "numberOfLetters": 24
    },
    {
      "answer": "Assigned Parking  Storage Space",
      "numberOfWords": 4,
      "numberOfLetters": 27
    },
    {
      "answer": "Associated  Panini Press",
      "numberOfWords": 3,
      "numberOfLetters": 21
    },
    {
      "answer": "Asssociated  Panini Press",
      "numberOfWords": 3,
      "numberOfLetters": 22
    },
    {
      "answer": "Astrology  Medical Chart",
      "numberOfWords": 3,
      "numberOfLetters": 21
    },
    {
      "answer": "Austin  Supernatural Powers",
      "numberOfWords": 3,
      "numberOfLetters": 24
    },
    {
      "answer": "Automatic  Handsome Pilot",
      "numberOfWords": 3,
      "numberOfLetters": 22
    },
    {
      "answer": "Awesome Architecture  Artwork",
      "numberOfWords": 3,
      "numberOfLetters": 26
    },
    {
      "answer": "BB  Chicken A La King",
      "numberOfWords": 5,
      "numberOfLetters": 16
    },
    {
      "answer": "Baby  Afternoon Shower",
      "numberOfWords": 3,
      "numberOfLetters": 19
    },
    {
      "answer": "Baby  April Shower",
      "numberOfWords": 3,
      "numberOfLetters": 15
    },
    {
      "answer": "Baby  Hall Monitor",
      "numberOfWords": 3,
      "numberOfLetters": 15
    },
    {
      "answer": "Baby  Secret Formula",
      "numberOfWords": 3,
      "numberOfLetters": 17
    },
    {
      "answer": "Baby And Chili Powder",
      "numberOfWords": 4,
      "numberOfLetters": 18
    },
    {
      "answer": "Background  Rent Check",
      "numberOfWords": 3,
      "numberOfLetters": 19
    },
    {
      "answer": "Baked And Exported Goods",
      "numberOfWords": 4,
      "numberOfLetters": 21
    },
    {
      "answer": "Bakers  Dirty Dozen",
      "numberOfWords": 3,
      "numberOfLetters": 16
    },
    {
      "answer": "Baking  Baby Powder",
      "numberOfWords": 3,
      "numberOfLetters": 16
    },
    {
      "answer": "Baking  Blasting Powder",
      "numberOfWords": 3,
      "numberOfLetters": 20
    },
    {
      "answer": "Baking  Diet Soda",
      "numberOfWords": 3,
      "numberOfLetters": 14
    },
    {
      "answer": "Baking  Powder Puff",
      "numberOfWords": 3,
      "numberOfLetters": 16
    },
    {
      "answer": "Baking  Talcum Powder",
      "numberOfWords": 3,
      "numberOfLetters": 18
    },
    {
      "answer": "Ball  Hospital Gown",
      "numberOfWords": 3,
      "numberOfLetters": 16
    },
    {
      "answer": "Ballet  Desmond Tutu",
      "numberOfWords": 3,
      "numberOfLetters": 17
    },
    {
      "answer": "Ballot  Gift Box",
      "numberOfWords": 3,
      "numberOfLetters": 13
    },
    {
      "answer": "Ballot  Suggestion Box",
      "numberOfWords": 3,
      "numberOfLetters": 19
    },
    {
      "answer": "Ballpoint  Finepoint Pen",
      "numberOfWords": 3,
      "numberOfLetters": 21
    },
    {
      "answer": "Bank  Fortune Teller",
      "numberOfWords": 3,
      "numberOfLetters": 17
    },
    {
      "answer": "Bank And Mineral Deposit",
      "numberOfWords": 4,
      "numberOfLetters": 21
    },
    {
      "answer": "Banquet And Coffee Table",
      "numberOfWords": 4,
      "numberOfLetters": 21
    },
    {
      "answer": "Bargaining  Potato Chip",
      "numberOfWords": 3,
      "numberOfLetters": 20
    },
    {
      "answer": "Barry  Savings Bonds",
      "numberOfWords": 3,
      "numberOfLetters": 17
    },
    {
      "answer": "Baseball  Hope Diamond",
      "numberOfWords": 3,
      "numberOfLetters": 19
    },
    {
      "answer": "Baseball  Winter Season",
      "numberOfWords": 3,
      "numberOfLetters": 20
    },
    {
      "answer": "Basic  Potty Training",
      "numberOfWords": 3,
      "numberOfLetters": 18
    },
    {
      "answer": "Bass  Treble Clef",
      "numberOfWords": 3,
      "numberOfLetters": 14
    },
    {
      "answer": "Bathing  Business Suit",
      "numberOfWords": 3,
      "numberOfLetters": 19
    },
    {
      "answer": "Bathroom  Fish Scale",
      "numberOfWords": 3,
      "numberOfLetters": 17
    },
    {
      "answer": "Bathroom  Horse Stall",
      "numberOfWords": 3,
      "numberOfLetters": 18
    },
    {
      "answer": "Bear  Bull Market",
      "numberOfWords": 3,
      "numberOfLetters": 14
    },
    {
      "answer": "Beautiful Babys Breath Bouquet",
      "numberOfWords": 4,
      "numberOfLetters": 27
    },
    {
      "answer": "Beauty  Question Mark",
      "numberOfWords": 3,
      "numberOfLetters": 18
    },
    {
      "answer": "Beaver  Meat Cleaver",
      "numberOfWords": 3,
      "numberOfLetters": 17
    },
    {
      "answer": "Ben  Aretha Franklin",
      "numberOfWords": 3,
      "numberOfLetters": 17
    },
    {
      "answer": "Bengal  Detroit Tigers",
      "numberOfWords": 3,
      "numberOfLetters": 19
    },
    {
      "answer": "Bermuda  Short Shorts",
      "numberOfWords": 3,
      "numberOfLetters": 18
    },
    {
      "answer": "Beverly Hills  Top Cop",
      "numberOfWords": 4,
      "numberOfLetters": 18
    },
    {
      "answer": "Bicycle  Food Chain",
      "numberOfWords": 3,
      "numberOfLetters": 16
    },
    {
      "answer": "Bicycle And Food Chain",
      "numberOfWords": 4,
      "numberOfLetters": 19
    },
    {
      "answer": "Bikinis  Swim Trunks",
      "numberOfWords": 3,
      "numberOfLetters": 17
    },
    {
      "answer": "Bill Of  Voting Rights",
      "numberOfWords": 4,
      "numberOfLetters": 18
    },
    {
      "answer": "Bills Of  Voting Rights",
      "numberOfWords": 4,
      "numberOfLetters": 19
    },
    {
      "answer": "Black Buckle Boots",
      "numberOfWords": 3,
      "numberOfLetters": 16
    },
    {
      "answer": "Block  Tailgate Party",
      "numberOfWords": 3,
      "numberOfLetters": 18
    },
    {
      "answer": "Blue And Full Moon",
      "numberOfWords": 4,
      "numberOfLetters": 15
    },
    {
      "answer": "BlueRibbon  Plywood Panel",
      "numberOfWords": 3,
      "numberOfLetters": 22
    },
    {
      "answer": "Bo  Jesse Jackson",
      "numberOfWords": 3,
      "numberOfLetters": 14
    },
    {
      "answer": "Bo  Luke Duke",
      "numberOfWords": 3,
      "numberOfLetters": 10
    },
    {
      "answer": "Bo And Jesse Jackson",
      "numberOfWords": 4,
      "numberOfLetters": 17
    },
    {
      "answer": "Boarding  Hall Pass",
      "numberOfWords": 3,
      "numberOfLetters": 16
    },
    {
      "answer": "Bob  Carnival Barker",
      "numberOfWords": 3,
      "numberOfLetters": 17
    },
    {
      "answer": "Bottomless  Cherry Pit",
      "numberOfWords": 3,
      "numberOfLetters": 19
    },
    {
      "answer": "Bowling  Carpool Lane",
      "numberOfWords": 3,
      "numberOfLetters": 18
    },
    {
      "answer": "Bowling And Dark Alley",
      "numberOfWords": 4,
      "numberOfLetters": 19
    },
    {
      "answer": "Boxing  Mix And Match",
      "numberOfWords": 4,
      "numberOfLetters": 17
    },
    {
      "answer": "Bradley  Gary Cooper",
      "numberOfWords": 3,
      "numberOfLetters": 17
    },
    {
      "answer": "Brantley  Sara Gilbert",
      "numberOfWords": 3,
      "numberOfLetters": 19
    },
    {
      "answer": "Bridal  April Shower",
      "numberOfWords": 3,
      "numberOfLetters": 17
    },
    {
      "answer": "Bridal  Formal Gown",
      "numberOfWords": 3,
      "numberOfLetters": 16
    },
    {
      "answer": "Browser  Sugar Cookies",
      "numberOfWords": 3,
      "numberOfLetters": 19
    },
    {
      "answer": "Bruno  Men From Mars",
      "numberOfWords": 4,
      "numberOfLetters": 16
    },
    {
      "answer": "Bubble  Movie Screen",
      "numberOfWords": 3,
      "numberOfLetters": 17
    },
    {
      "answer": "Bubble  Thermal Wrap",
      "numberOfWords": 3,
      "numberOfLetters": 17
    },
    {
      "answer": "Bubble Bath Bombs",
      "numberOfWords": 3,
      "numberOfLetters": 15
    },
    {
      "answer": "Buffalo  Paid Bills",
      "numberOfWords": 3,
      "numberOfLetters": 16
    },
    {
      "answer": "Buffalo  Telephone Bills",
      "numberOfWords": 3,
      "numberOfLetters": 21
    },
    {
      "answer": "Bugs  Dumb Bunny",
      "numberOfWords": 3,
      "numberOfLetters": 13
    },
    {
      "answer": "Bull  Tiger Shark",
      "numberOfWords": 3,
      "numberOfLetters": 14
    },
    {
      "answer": "Bull And Tiger Shark",
      "numberOfWords": 4,
      "numberOfLetters": 17
    },
    {
      "answer": "Bulletproof  Tuxedo Vest",
      "numberOfWords": 3,
      "numberOfLetters": 21
    },
    {
      "answer": "Burlese And Green Tree Python",
      "numberOfWords": 5,
      "numberOfLetters": 25
    },
    {
      "answer": "Burmese  Green Tree Python",
      "numberOfWords": 4,
      "numberOfLetters": 22
    },
    {
      "answer": "Business  Casual Attire",
      "numberOfWords": 3,
      "numberOfLetters": 20
    },
    {
      "answer": "Business  Family Trip",
      "numberOfWords": 3,
      "numberOfLetters": 18
    },
    {
      "answer": "Busy As A  Aunt Bee",
      "numberOfWords": 5,
      "numberOfLetters": 14
    },
    {
      "answer": "Calming  Adverse Effect",
      "numberOfWords": 3,
      "numberOfLetters": 20
    },
    {
      "answer": "Campaign  Charitable Donations",
      "numberOfWords": 3,
      "numberOfLetters": 27
    },
    {
      "answer": "Campaign  Hiking Trail",
      "numberOfWords": 3,
      "numberOfLetters": 19
    },
    {
      "answer": "Campaign  Mute Button",
      "numberOfWords": 3,
      "numberOfLetters": 18
    },
    {
      "answer": "Campaign And Hiking Trail",
      "numberOfWords": 4,
      "numberOfLetters": 22
    },
    {
      "answer": "Campaign And Mute Button",
      "numberOfWords": 4,
      "numberOfLetters": 21
    },
    {
      "answer": "Candle  Fruit Wax",
      "numberOfWords": 3,
      "numberOfLetters": 14
    },
    {
      "answer": "Candy  Karaoke Bars",
      "numberOfWords": 3,
      "numberOfLetters": 16
    },
    {
      "answer": "Candy  Pull Up Bar",
      "numberOfWords": 4,
      "numberOfLetters": 14
    },
    {
      "answer": "Candy  PullUp Bar",
      "numberOfWords": 3,
      "numberOfLetters": 14
    },
    {
      "answer": "Candy And Karaoke Bars",
      "numberOfWords": 4,
      "numberOfLetters": 19
    },
    {
      "answer": "Canoe  Fraternity Paddle",
      "numberOfWords": 3,
      "numberOfLetters": 21
    },
    {
      "answer": "Capital  Lowercase Letters",
      "numberOfWords": 3,
      "numberOfLetters": 23
    },
    {
      "answer": "Capitol  Lauryn Hill",
      "numberOfWords": 3,
      "numberOfLetters": 17
    },
    {
      "answer": "Card  Nurse Shark",
      "numberOfWords": 3,
      "numberOfLetters": 14
    },
    {
      "answer": "Career  Hidden Path",
      "numberOfWords": 3,
      "numberOfLetters": 16
    },
    {
      "answer": "Cargo  Escape Hatch",
      "numberOfWords": 3,
      "numberOfLetters": 16
    },
    {
      "answer": "Carpool  Diane Lane",
      "numberOfWords": 3,
      "numberOfLetters": 16
    },
    {
      "answer": "Carrot  Popsicle Sticks",
      "numberOfWords": 3,
      "numberOfLetters": 20
    },
    {
      "answer": "Carrying A  Tommy Tune",
      "numberOfWords": 4,
      "numberOfLetters": 18
    },
    {
      "answer": "Cash  Weekly Allowance",
      "numberOfWords": 3,
      "numberOfLetters": 19
    },
    {
      "answer": "Casserole  Satellite Dish",
      "numberOfWords": 3,
      "numberOfLetters": 22
    },
    {
      "answer": "Casual  Freaky Friday",
      "numberOfWords": 3,
      "numberOfLetters": 18
    },
    {
      "answer": "Cat  Back Scratcher",
      "numberOfWords": 3,
      "numberOfLetters": 16
    },
    {
      "answer": "Cat  Pick Up Your Litter",
      "numberOfWords": 5,
      "numberOfLetters": 19
    },
    {
      "answer": "Cave  Lottery Drawing",
      "numberOfWords": 3,
      "numberOfLetters": 18
    },
    {
      "answer": "Celebrity  Weenie Roast",
      "numberOfWords": 3,
      "numberOfLetters": 20
    },
    {
      "answer": "Celebrity And Wennie Roast",
      "numberOfWords": 4,
      "numberOfLetters": 23
    },
    {
      "answer": "Central Nervous  Computer System",
      "numberOfWords": 4,
      "numberOfLetters": 28
    },
    {
      "answer": "Cereal  Toilet Bowl",
      "numberOfWords": 3,
      "numberOfLetters": 16
    },
    {
      "answer": "Champagne  Burnt Toast",
      "numberOfWords": 3,
      "numberOfLetters": 19
    },
    {
      "answer": "Champagne  Wheat Toast",
      "numberOfWords": 3,
      "numberOfLetters": 19
    },
    {
      "answer": "Cherry  Plum Tarts",
      "numberOfWords": 3,
      "numberOfLetters": 15
    },
    {
      "answer": "Chicago  Black Bears",
      "numberOfWords": 3,
      "numberOfLetters": 17
    },
    {
      "answer": "Chicago  Cheetah Cubs",
      "numberOfWords": 3,
      "numberOfLetters": 18
    },
    {
      "answer": "Chicago  Grizzly Bears",
      "numberOfWords": 3,
      "numberOfLetters": 19
    },
    {
      "answer": "Chicago And Grizzly Bears",
      "numberOfWords": 4,
      "numberOfLetters": 22
    },
    {
      "answer": "Chicken  Airplane Wings",
      "numberOfWords": 3,
      "numberOfLetters": 20
    },
    {
      "answer": "Chicken  Beef Broth",
      "numberOfWords": 3,
      "numberOfLetters": 16
    },
    {
      "answer": "Chicken And Airplane Wings",
      "numberOfWords": 4,
      "numberOfLetters": 23
    },
    {
      "answer": "Chigaco And Cheetah Cubs",
      "numberOfWords": 4,
      "numberOfLetters": 21
    },
    {
      "answer": "Chuck  Halle Berry",
      "numberOfWords": 3,
      "numberOfLetters": 15
    },
    {
      "answer": "Circus  Oxygen Tent",
      "numberOfWords": 3,
      "numberOfLetters": 16
    },
    {
      "answer": "Citizen  Carol Kane",
      "numberOfWords": 3,
      "numberOfLetters": 16
    },
    {
      "answer": "Citizen And Carol Kane",
      "numberOfWords": 4,
      "numberOfLetters": 19
    },
    {
      "answer": "Claire  Great Danes",
      "numberOfWords": 3,
      "numberOfLetters": 16
    },
    {
      "answer": "Clay  Veggie Wrap",
      "numberOfWords": 3,
      "numberOfLetters": 14
    },
    {
      "answer": "Climbing  Ships Anchor",
      "numberOfWords": 3,
      "numberOfLetters": 19
    },
    {
      "answer": "Climbing  Ships Anchor",
      "numberOfWords": 3,
      "numberOfLetters": 19
    },
    {
      "answer": "Clinical  Jury Trial",
      "numberOfWords": 3,
      "numberOfLetters": 17
    },
    {
      "answer": "Clint  Fade To Black",
      "numberOfWords": 4,
      "numberOfLetters": 16
    },
    {
      "answer": "Coffee And Lucky Break",
      "numberOfWords": 4,
      "numberOfLetters": 19
    },
    {
      "answer": "Coffee And Organ Grinder",
      "numberOfWords": 4,
      "numberOfLetters": 21
    },
    {
      "answer": "College  A Class President",
      "numberOfWords": 4,
      "numberOfLetters": 22
    },
    {
      "answer": "College  Class President",
      "numberOfWords": 3,
      "numberOfLetters": 21
    },
    {
      "answer": "Common  Bank Vole",
      "numberOfWords": 3,
      "numberOfLetters": 14
    },
    {
      "answer": "Common  Proper Noun",
      "numberOfWords": 3,
      "numberOfLetters": 16
    },
    {
      "answer": "Common And Proper Noun",
      "numberOfWords": 4,
      "numberOfLetters": 19
    },
    {
      "answer": "Construction  Comfort Zone",
      "numberOfWords": 3,
      "numberOfLetters": 23
    },
    {
      "answer": "Contact  Shopping List",
      "numberOfWords": 3,
      "numberOfLetters": 19
    },
    {
      "answer": "Cookie  Frankensteins Monster",
      "numberOfWords": 3,
      "numberOfLetters": 26
    },
    {
      "answer": "Cookie  Member Of The Press",
      "numberOfWords": 5,
      "numberOfLetters": 22
    },
    {
      "answer": "Cooking  Outer Space",
      "numberOfWords": 3,
      "numberOfLetters": 17
    },
    {
      "answer": "Cough  Mail Drop",
      "numberOfWords": 3,
      "numberOfLetters": 13
    },
    {
      "answer": "Cough  Rain Drop",
      "numberOfWords": 3,
      "numberOfLetters": 13
    },
    {
      "answer": "County  Childs Car Seat",
      "numberOfWords": 4,
      "numberOfLetters": 19
    },
    {
      "answer": "Court  News Reporter",
      "numberOfWords": 3,
      "numberOfLetters": 17
    },
    {
      "answer": "Court  Shipping Clerk",
      "numberOfWords": 3,
      "numberOfLetters": 18
    },
    {
      "answer": "Cover  Electric Charge",
      "numberOfWords": 3,
      "numberOfLetters": 19
    },
    {
      "answer": "Covered  Dessert Dish",
      "numberOfWords": 3,
      "numberOfLetters": 18
    },
    {
      "answer": "Cows  Shoe Tongue",
      "numberOfWords": 3,
      "numberOfLetters": 14
    },
    {
      "answer": "Cows And Shoe Tongue",
      "numberOfWords": 4,
      "numberOfLetters": 17
    },
    {
      "answer": "Credit  Birthday Card",
      "numberOfWords": 3,
      "numberOfLetters": 18
    },
    {
      "answer": "Crew And Butchers Cut",
      "numberOfWords": 4,
      "numberOfLetters": 18
    },
    {
      "answer": "Crop  Earths Rotation",
      "numberOfWords": 3,
      "numberOfLetters": 18
    },
    {
      "answer": "Crunchy Coconut Chips",
      "numberOfWords": 3,
      "numberOfLetters": 19
    },
    {
      "answer": "Culinary  Chicken Delight",
      "numberOfWords": 3,
      "numberOfLetters": 22
    },
    {
      "answer": "Culture  Country Club",
      "numberOfWords": 3,
      "numberOfLetters": 18
    },
    {
      "answer": "Cupid  Green Arrow",
      "numberOfWords": 3,
      "numberOfLetters": 15
    },
    {
      "answer": "Cupids  Green Arrow",
      "numberOfWords": 3,
      "numberOfLetters": 16
    },
    {
      "answer": "Curtain  WakeUp Call",
      "numberOfWords": 3,
      "numberOfLetters": 17
    },
    {
      "answer": "Cutting  Bulletin Board",
      "numberOfWords": 3,
      "numberOfLetters": 20
    },
    {
      "answer": "Dance  Piano Recital",
      "numberOfWords": 3,
      "numberOfLetters": 17
    },
    {
      "answer": "Dancing  Dairy Queen",
      "numberOfWords": 3,
      "numberOfLetters": 17
    },
    {
      "answer": "Darning  Overcast Stitch",
      "numberOfWords": 3,
      "numberOfLetters": 21
    },
    {
      "answer": "Data  Escape Plan",
      "numberOfWords": 3,
      "numberOfLetters": 14
    },
    {
      "answer": "Date  Honey Shake",
      "numberOfWords": 3,
      "numberOfLetters": 14
    },
    {
      "answer": "Defensive  Scratch My Back",
      "numberOfWords": 4,
      "numberOfLetters": 22
    },
    {
      "answer": "Delicious Dessert Dips",
      "numberOfWords": 3,
      "numberOfLetters": 20
    },
    {
      "answer": "Dennis  Glenn Miller",
      "numberOfWords": 3,
      "numberOfLetters": 17
    },
    {
      "answer": "Dessert  Home Plate",
      "numberOfWords": 3,
      "numberOfLetters": 16
    },
    {
      "answer": "Diamond  Boxing Ring",
      "numberOfWords": 3,
      "numberOfLetters": 17
    },
    {
      "answer": "Diana  Betsy Ross",
      "numberOfWords": 3,
      "numberOfLetters": 14
    },
    {
      "answer": "Diane  Carpool Lane",
      "numberOfWords": 3,
      "numberOfLetters": 16
    },
    {
      "answer": "Diane  Country Lane",
      "numberOfWords": 3,
      "numberOfLetters": 16
    },
    {
      "answer": "Diaper  Mop Pail",
      "numberOfWords": 3,
      "numberOfLetters": 13
    },
    {
      "answer": "Dinner  Liberty Bell",
      "numberOfWords": 3,
      "numberOfLetters": 17
    },
    {
      "answer": "Dinner  Uninvited Guests",
      "numberOfWords": 3,
      "numberOfLetters": 21
    },
    {
      "answer": "Directors  Butchers Cut",
      "numberOfWords": 3,
      "numberOfLetters": 20
    },
    {
      "answer": "Dive And Sundae Bar",
      "numberOfWords": 4,
      "numberOfLetters": 16
    },
    {
      "answer": "Diving  School Board",
      "numberOfWords": 3,
      "numberOfLetters": 17
    },
    {
      "answer": "Diving And School Board",
      "numberOfWords": 4,
      "numberOfLetters": 20
    },
    {
      "answer": "Dog  Buttermilk Biscuits",
      "numberOfWords": 3,
      "numberOfLetters": 21
    },
    {
      "answer": "Doggie  Grocery Bag",
      "numberOfWords": 3,
      "numberOfLetters": 16
    },
    {
      "answer": "Dogwood  Family Tree",
      "numberOfWords": 3,
      "numberOfLetters": 17
    },
    {
      "answer": "Dont Rain On My  Easter Parade",
      "numberOfWords": 6,
      "numberOfLetters": 24
    },
    {
      "answer": "Doomsday And General Zod",
      "numberOfWords": 4,
      "numberOfLetters": 21
    },
    {
      "answer": "Door  Booby Prize",
      "numberOfWords": 3,
      "numberOfLetters": 14
    },
    {
      "answer": "DooWop  Scientific Groups",
      "numberOfWords": 3,
      "numberOfLetters": 22
    },
    {
      "answer": "Drastic  Tape Measure",
      "numberOfWords": 3,
      "numberOfLetters": 18
    },
    {
      "answer": "Dried Onion  Class Ring",
      "numberOfWords": 4,
      "numberOfLetters": 19
    },
    {
      "answer": "Driving  Main Course",
      "numberOfWords": 3,
      "numberOfLetters": 17
    },
    {
      "answer": "Driving  Memory Lane",
      "numberOfWords": 3,
      "numberOfLetters": 17
    },
    {
      "answer": "Dry  Floating Dock",
      "numberOfWords": 3,
      "numberOfLetters": 15
    },
    {
      "answer": "Duck  Anonymous Call",
      "numberOfWords": 3,
      "numberOfLetters": 17
    },
    {
      "answer": "Duke  Cat Ellington",
      "numberOfWords": 3,
      "numberOfLetters": 16
    },
    {
      "answer": "Dustin  Jane Lynch",
      "numberOfWords": 3,
      "numberOfLetters": 15
    },
    {
      "answer": "Dustin And Jane Lynch",
      "numberOfWords": 4,
      "numberOfLetters": 18
    },
    {
      "answer": "Ear  Snare Drum",
      "numberOfWords": 3,
      "numberOfLetters": 12
    },
    {
      "answer": "Earned  Piqued My Interest",
      "numberOfWords": 4,
      "numberOfLetters": 22
    },
    {
      "answer": "Earned And Piqued My Interest",
      "numberOfWords": 5,
      "numberOfLetters": 25
    },
    {
      "answer": "Earring  Fishing Hook",
      "numberOfWords": 3,
      "numberOfLetters": 18
    },
    {
      "answer": "Earthly  Tree Branches",
      "numberOfWords": 3,
      "numberOfLetters": 19
    },
    {
      "answer": "East  West Coast",
      "numberOfWords": 3,
      "numberOfLetters": 13
    },
    {
      "answer": "East And Challenging Trails",
      "numberOfWords": 4,
      "numberOfLetters": 24
    },
    {
      "answer": "Easter And Dust Bunny",
      "numberOfWords": 4,
      "numberOfLetters": 18
    },
    {
      "answer": "Easy  Challenging Trails",
      "numberOfWords": 3,
      "numberOfLetters": 21
    },
    {
      "answer": "Elastic  Jazz Band",
      "numberOfWords": 3,
      "numberOfLetters": 15
    },
    {
      "answer": "Elastic And Jazz Band",
      "numberOfWords": 4,
      "numberOfLetters": 18
    },
    {
      "answer": "Elbow  Shoulder Pads",
      "numberOfWords": 3,
      "numberOfLetters": 17
    },
    {
      "answer": "Election  Positive Results",
      "numberOfWords": 3,
      "numberOfLetters": 23
    },
    {
      "answer": "Election  Test Results",
      "numberOfWords": 3,
      "numberOfLetters": 19
    },
    {
      "answer": "Election And Test Results",
      "numberOfWords": 4,
      "numberOfLetters": 22
    },
    {
      "answer": "Electoral  Community College",
      "numberOfWords": 3,
      "numberOfLetters": 25
    },
    {
      "answer": "Electrical  Orchestra Conductor",
      "numberOfWords": 3,
      "numberOfLetters": 28
    },
    {
      "answer": "Elm And Family Tree",
      "numberOfWords": 4,
      "numberOfLetters": 16
    },
    {
      "answer": "Embroidery  House Key",
      "numberOfWords": 3,
      "numberOfLetters": 18
    },
    {
      "answer": "Emma  Pumice Stone",
      "numberOfWords": 3,
      "numberOfLetters": 15
    },
    {
      "answer": "Emperor  Pittsburgh Penguins",
      "numberOfWords": 3,
      "numberOfLetters": 25
    },
    {
      "answer": "Energy  Karaoke Bar",
      "numberOfWords": 3,
      "numberOfLetters": 16
    },
    {
      "answer": "Energy  Karoke Bar",
      "numberOfWords": 3,
      "numberOfLetters": 15
    },
    {
      "answer": "Entrance  Written Exam",
      "numberOfWords": 3,
      "numberOfLetters": 19
    },
    {
      "answer": "Exclamation  Make Your Point",
      "numberOfWords": 4,
      "numberOfLetters": 24
    },
    {
      "answer": "Executive  Breakfast Order",
      "numberOfWords": 3,
      "numberOfLetters": 23
    },
    {
      "answer": "Exercise  Dance Routine",
      "numberOfWords": 3,
      "numberOfLetters": 20
    },
    {
      "answer": "Exhaust  Corncob Pipe",
      "numberOfWords": 3,
      "numberOfLetters": 18
    },
    {
      "answer": "Eye  FiveOClock Shadow",
      "numberOfWords": 3,
      "numberOfLetters": 19
    },
    {
      "answer": "Eye And Oral Exam",
      "numberOfWords": 4,
      "numberOfLetters": 14
    },
    {
      "answer": "Eyebrow  Mechanical Pencil",
      "numberOfWords": 3,
      "numberOfLetters": 23
    },
    {
      "answer": "Eyebrow And Mechanical Pencil",
      "numberOfWords": 4,
      "numberOfLetters": 26
    },
    {
      "answer": "Fabulous  Marine Mysteries",
      "numberOfWords": 3,
      "numberOfLetters": 23
    },
    {
      "answer": "Face  Extra Value",
      "numberOfWords": 3,
      "numberOfLetters": 14
    },
    {
      "answer": "Faith  Bunker Hill",
      "numberOfWords": 3,
      "numberOfLetters": 15
    },
    {
      "answer": "Faith And Lauryn Hill",
      "numberOfWords": 4,
      "numberOfLetters": 18
    },
    {
      "answer": "Family  Club Members",
      "numberOfWords": 3,
      "numberOfLetters": 17
    },
    {
      "answer": "Fan  First Base",
      "numberOfWords": 3,
      "numberOfLetters": 12
    },
    {
      "answer": "Farmer  Elton John",
      "numberOfWords": 3,
      "numberOfLetters": 15
    },
    {
      "answer": "Fashion  Bank Statement",
      "numberOfWords": 3,
      "numberOfLetters": 20
    },
    {
      "answer": "Film  Motley Crew",
      "numberOfWords": 3,
      "numberOfLetters": 14
    },
    {
      "answer": "Finger  Super Bowl",
      "numberOfWords": 3,
      "numberOfLetters": 15
    },
    {
      "answer": "Fire  Indian Chief",
      "numberOfWords": 3,
      "numberOfLetters": 15
    },
    {
      "answer": "Fireworks  Window Display",
      "numberOfWords": 3,
      "numberOfLetters": 22
    },
    {
      "answer": "Fish And Gas Tank",
      "numberOfWords": 4,
      "numberOfLetters": 14
    },
    {
      "answer": "Fishing  Lightning Rod",
      "numberOfWords": 3,
      "numberOfLetters": 19
    },
    {
      "answer": "Fishing  North Pole",
      "numberOfWords": 3,
      "numberOfLetters": 16
    },
    {
      "answer": "Fishing And North Pole",
      "numberOfWords": 4,
      "numberOfLetters": 19
    },
    {
      "answer": "Fitness  Daily Routine",
      "numberOfWords": 3,
      "numberOfLetters": 19
    },
    {
      "answer": "Fitness  Economy Class",
      "numberOfWords": 3,
      "numberOfLetters": 19
    },
    {
      "answer": "Flamenco  Disco Dancer",
      "numberOfWords": 3,
      "numberOfLetters": 19
    },
    {
      "answer": "Fleetwood  Big Mac",
      "numberOfWords": 3,
      "numberOfLetters": 15
    },
    {
      "answer": "Florida  Car Keys",
      "numberOfWords": 3,
      "numberOfLetters": 14
    },
    {
      "answer": "Flower  Taste Buds",
      "numberOfWords": 3,
      "numberOfLetters": 15
    },
    {
      "answer": "Focal  Breaking Point",
      "numberOfWords": 3,
      "numberOfLetters": 18
    },
    {
      "answer": "Folic  Hydrochloric Acid",
      "numberOfWords": 3,
      "numberOfLetters": 21
    },
    {
      "answer": "Football  Playing Field",
      "numberOfWords": 3,
      "numberOfLetters": 20
    },
    {
      "answer": "Football And New Jersey",
      "numberOfWords": 4,
      "numberOfLetters": 20
    },
    {
      "answer": "Fraternal  Court Order",
      "numberOfWords": 3,
      "numberOfLetters": 19
    },
    {
      "answer": "Freezing  Boiling Point",
      "numberOfWords": 3,
      "numberOfLetters": 20
    },
    {
      "answer": "Freudian And Permission Slip",
      "numberOfWords": 4,
      "numberOfLetters": 25
    },
    {
      "answer": "Fried Onion  Class Ring",
      "numberOfWords": 4,
      "numberOfLetters": 19
    },
    {
      "answer": "FriedOnion  Class Ring",
      "numberOfWords": 3,
      "numberOfLetters": 19
    },
    {
      "answer": "Froot  Belt Loops",
      "numberOfWords": 3,
      "numberOfLetters": 14
    },
    {
      "answer": "Fruit  Knockout Punch",
      "numberOfWords": 3,
      "numberOfLetters": 18
    },
    {
      "answer": "Frying  Flash In The Pan",
      "numberOfWords": 5,
      "numberOfLetters": 19
    },
    {
      "answer": "Fuel  Water Pump",
      "numberOfWords": 3,
      "numberOfLetters": 13
    },
    {
      "answer": "Funeral  Sterling Silver Service",
      "numberOfWords": 4,
      "numberOfLetters": 28
    },
    {
      "answer": "Funeral  SterlingSilver Service",
      "numberOfWords": 3,
      "numberOfLetters": 28
    },
    {
      "answer": "Future  Flight Plan",
      "numberOfWords": 3,
      "numberOfLetters": 16
    },
    {
      "answer": "Garden  Bunk Bed",
      "numberOfWords": 3,
      "numberOfLetters": 13
    },
    {
      "answer": "Garlic  Baby Powder",
      "numberOfWords": 3,
      "numberOfLetters": 16
    },
    {
      "answer": "Garter  Bible Belt",
      "numberOfWords": 3,
      "numberOfLetters": 15
    },
    {
      "answer": "Garth  Mel Brooks",
      "numberOfWords": 3,
      "numberOfLetters": 14
    },
    {
      "answer": "Gas  Army Tank",
      "numberOfWords": 3,
      "numberOfLetters": 11
    },
    {
      "answer": "Gas  Water Pump",
      "numberOfWords": 3,
      "numberOfLetters": 12
    },
    {
      "answer": "Gasoline  Water Pump",
      "numberOfWords": 3,
      "numberOfLetters": 17
    },
    {
      "answer": "Gee  Cheez Whiz",
      "numberOfWords": 3,
      "numberOfLetters": 12
    },
    {
      "answer": "Geologic  Official Record",
      "numberOfWords": 3,
      "numberOfLetters": 22
    },
    {
      "answer": "George  Bering Strait",
      "numberOfWords": 3,
      "numberOfLetters": 18
    },
    {
      "answer": "George  Lake Washington",
      "numberOfWords": 3,
      "numberOfLetters": 20
    },
    {
      "answer": "George  Walla Walla Washington",
      "numberOfWords": 4,
      "numberOfLetters": 26
    },
    {
      "answer": "Gerald  Henry Ford",
      "numberOfWords": 3,
      "numberOfLetters": 15
    },
    {
      "answer": "Geraldo  Chita Rivera",
      "numberOfWords": 3,
      "numberOfLetters": 18
    },
    {
      "answer": "Gettysburg  Home Address",
      "numberOfWords": 3,
      "numberOfLetters": 21
    },
    {
      "answer": "Gilded  Lying About My Age",
      "numberOfWords": 5,
      "numberOfLetters": 21
    },
    {
      "answer": "Glamour  Puss In Boots",
      "numberOfWords": 4,
      "numberOfLetters": 18
    },
    {
      "answer": "Gold  Wet Bar",
      "numberOfWords": 3,
      "numberOfLetters": 10
    },
    {
      "answer": "Golden  Bald Eagle",
      "numberOfWords": 3,
      "numberOfLetters": 15
    },
    {
      "answer": "Golden  Fallen Arches",
      "numberOfWords": 3,
      "numberOfLetters": 18
    },
    {
      "answer": "Golden  Telephone Ring",
      "numberOfWords": 3,
      "numberOfLetters": 19
    },
    {
      "answer": "Goldfish  Super Bowl",
      "numberOfWords": 3,
      "numberOfLetters": 17
    },
    {
      "answer": "Golf  Coffee Cart",
      "numberOfWords": 3,
      "numberOfLetters": 14
    },
    {
      "answer": "Good Will  Deer Hunting",
      "numberOfWords": 4,
      "numberOfLetters": 19
    },
    {
      "answer": "Government  Corporate Bonds",
      "numberOfWords": 3,
      "numberOfLetters": 24
    },
    {
      "answer": "Government And Corporate Bonds",
      "numberOfWords": 4,
      "numberOfLetters": 27
    },
    {
      "answer": "Granola And Monkey Bars",
      "numberOfWords": 4,
      "numberOfLetters": 20
    },
    {
      "answer": "Gravy  ChooChoo Train",
      "numberOfWords": 3,
      "numberOfLetters": 18
    },
    {
      "answer": "Gravy  Owning Boats",
      "numberOfWords": 3,
      "numberOfLetters": 16
    },
    {
      "answer": "Gravy  Rowing Boats",
      "numberOfWords": 3,
      "numberOfLetters": 16
    },
    {
      "answer": "Gravy  Sinking Boat",
      "numberOfWords": 3,
      "numberOfLetters": 16
    },
    {
      "answer": "Gray  Bowhead Whale",
      "numberOfWords": 3,
      "numberOfLetters": 16
    },
    {
      "answer": "Great White  San Jose Sharks",
      "numberOfWords": 5,
      "numberOfLetters": 23
    },
    {
      "answer": "Green  Tom Thumb",
      "numberOfWords": 3,
      "numberOfLetters": 13
    },
    {
      "answer": "Green Bay  Meat Packers",
      "numberOfWords": 4,
      "numberOfLetters": 19
    },
    {
      "answer": "Grevys  Plains Zebra",
      "numberOfWords": 3,
      "numberOfLetters": 17
    },
    {
      "answer": "Grizzly  Teddy Bear",
      "numberOfWords": 3,
      "numberOfLetters": 16
    },
    {
      "answer": "Groundhog  Doris Day",
      "numberOfWords": 3,
      "numberOfLetters": 17
    },
    {
      "answer": "Groundhog And Doris Day",
      "numberOfWords": 4,
      "numberOfLetters": 20
    },
    {
      "answer": "Guest  Family Pass",
      "numberOfWords": 3,
      "numberOfLetters": 15
    },
    {
      "answer": "Guest  Top Ten List",
      "numberOfWords": 4,
      "numberOfLetters": 15
    },
    {
      "answer": "Guitar  Soccer Player",
      "numberOfWords": 4,
      "numberOfLetters": 19
    },
    {
      "answer": "Guitar  Soccer Player",
      "numberOfWords": 3,
      "numberOfLetters": 18
    },
    {
      "answer": "Hair  Paper Clips",
      "numberOfWords": 3,
      "numberOfLetters": 14
    },
    {
      "answer": "Hair And Paper Clips",
      "numberOfWords": 4,
      "numberOfLetters": 17
    },
    {
      "answer": "Halloween  Facial Mask",
      "numberOfWords": 3,
      "numberOfLetters": 19
    },
    {
      "answer": "Hamburger  Move Your Buns",
      "numberOfWords": 4,
      "numberOfLetters": 21
    },
    {
      "answer": "Handwritten  Musical Note",
      "numberOfWords": 3,
      "numberOfLetters": 22
    },
    {
      "answer": "Handwritten  Musical Notes",
      "numberOfWords": 3,
      "numberOfLetters": 23
    },
    {
      "answer": "Handy Helpful Handbook",
      "numberOfWords": 3,
      "numberOfLetters": 20
    },
    {
      "answer": "Happy  Witching Hour",
      "numberOfWords": 3,
      "numberOfLetters": 17
    },
    {
      "answer": "Helmut  Fig Newton",
      "numberOfWords": 3,
      "numberOfLetters": 15
    },
    {
      "answer": "High  Late Middle Ages",
      "numberOfWords": 4,
      "numberOfLetters": 18
    },
    {
      "answer": "High  Low Season",
      "numberOfWords": 3,
      "numberOfLetters": 13
    },
    {
      "answer": "High  Low Visibility",
      "numberOfWords": 3,
      "numberOfLetters": 17
    },
    {
      "answer": "Highway  Solar System",
      "numberOfWords": 3,
      "numberOfLetters": 18
    },
    {
      "answer": "Hip  Clip Joint",
      "numberOfWords": 3,
      "numberOfLetters": 12
    },
    {
      "answer": "Hitching  Parcel Post",
      "numberOfWords": 3,
      "numberOfLetters": 18
    },
    {
      "answer": "Hitching  The Washington Post",
      "numberOfWords": 4,
      "numberOfLetters": 25
    },
    {
      "answer": "Hollywood  Stop Sign",
      "numberOfWords": 3,
      "numberOfLetters": 17
    },
    {
      "answer": "Homer  Jessica Simpson",
      "numberOfWords": 3,
      "numberOfLetters": 19
    },
    {
      "answer": "Homer And Jessica Simpson",
      "numberOfWords": 4,
      "numberOfLetters": 22
    },
    {
      "answer": "Honey Ham  Hotcakes",
      "numberOfWords": 3,
      "numberOfLetters": 16
    },
    {
      "answer": "Hong And King Kong",
      "numberOfWords": 4,
      "numberOfLetters": 15
    },
    {
      "answer": "Honor  Subway System",
      "numberOfWords": 3,
      "numberOfLetters": 17
    },
    {
      "answer": "Honor  Tootsie Roll",
      "numberOfWords": 3,
      "numberOfLetters": 16
    },
    {
      "answer": "Hospitality  Honeymoon Suite",
      "numberOfWords": 3,
      "numberOfLetters": 25
    },
    {
      "answer": "Hourglass  Ballpark Figure",
      "numberOfWords": 3,
      "numberOfLetters": 23
    },
    {
      "answer": "House  Car Keys",
      "numberOfWords": 3,
      "numberOfLetters": 12
    },
    {
      "answer": "I Cant Get No  Customer Satisfaction",
      "numberOfWords": 6,
      "numberOfLetters": 30
    },
    {
      "answer": "Icabod  Whooping Crane",
      "numberOfWords": 3,
      "numberOfLetters": 19
    },
    {
      "answer": "Ice Cream And Pine Cone",
      "numberOfWords": 5,
      "numberOfLetters": 19
    },
    {
      "answer": "Ichabod  Whooping Crane",
      "numberOfWords": 3,
      "numberOfLetters": 20
    },
    {
      "answer": "In The Drivers  Hot Seat",
      "numberOfWords": 5,
      "numberOfLetters": 19
    },
    {
      "answer": "Indiana  Norah Jones",
      "numberOfWords": 3,
      "numberOfLetters": 17
    },
    {
      "answer": "Inferiority  Apartment Complex",
      "numberOfWords": 3,
      "numberOfLetters": 27
    },
    {
      "answer": "Inland  Roman Empire",
      "numberOfWords": 3,
      "numberOfLetters": 17
    },
    {
      "answer": "Inner  Outer Arch",
      "numberOfWords": 3,
      "numberOfLetters": 14
    },
    {
      "answer": "Inner And Outer Arch",
      "numberOfWords": 4,
      "numberOfLetters": 17
    },
    {
      "answer": "Instanbul  Stuffed Turkey",
      "numberOfWords": 3,
      "numberOfLetters": 22
    },
    {
      "answer": "Insurance  Free Agent",
      "numberOfWords": 3,
      "numberOfLetters": 18
    },
    {
      "answer": "Intelligent Idealistic Inventors",
      "numberOfWords": 3,
      "numberOfLetters": 30
    },
    {
      "answer": "Internet  Love Connection",
      "numberOfWords": 3,
      "numberOfLetters": 22
    },
    {
      "answer": "Irish  Jet Setter",
      "numberOfWords": 3,
      "numberOfLetters": 14
    },
    {
      "answer": "Iron  Make A Fist",
      "numberOfWords": 4,
      "numberOfLetters": 13
    },
    {
      "answer": "Island And Bicycle Chain",
      "numberOfWords": 4,
      "numberOfLetters": 21
    },
    {
      "answer": "Istanbul And Stuffed Turkey",
      "numberOfWords": 4,
      "numberOfLetters": 24
    },
    {
      "answer": "Itunes  School Library",
      "numberOfWords": 3,
      "numberOfLetters": 19
    },
    {
      "answer": "Jackie  Benny Chan",
      "numberOfWords": 3,
      "numberOfLetters": 15
    },
    {
      "answer": "James  Savings Bond",
      "numberOfWords": 3,
      "numberOfLetters": 16
    },
    {
      "answer": "Jean  Joel Grey",
      "numberOfWords": 3,
      "numberOfLetters": 12
    },
    {
      "answer": "Jennifer  Vicki Lawrence",
      "numberOfWords": 3,
      "numberOfLetters": 21
    },
    {
      "answer": "Jet  Irish Setter",
      "numberOfWords": 3,
      "numberOfLetters": 14
    },
    {
      "answer": "Jodie  Banana Foster",
      "numberOfWords": 3,
      "numberOfLetters": 17
    },
    {
      "answer": "Jodie  Bananas Foster",
      "numberOfWords": 3,
      "numberOfLetters": 18
    },
    {
      "answer": "Johann  Levi Strauss",
      "numberOfWords": 3,
      "numberOfLetters": 17
    },
    {
      "answer": "Juice  Isaac Newton",
      "numberOfWords": 3,
      "numberOfLetters": 16
    },
    {
      "answer": "Jungle  Private Gym",
      "numberOfWords": 3,
      "numberOfLetters": 16
    },
    {
      "answer": "Junior  Executive Suite",
      "numberOfWords": 3,
      "numberOfLetters": 20
    },
    {
      "answer": "Jury  Civil Duty",
      "numberOfWords": 3,
      "numberOfLetters": 13
    },
    {
      "answer": "Justice  Bowling League",
      "numberOfWords": 3,
      "numberOfLetters": 20
    },
    {
      "answer": "Justice  Bowling Legue",
      "numberOfWords": 3,
      "numberOfLetters": 19
    },
    {
      "answer": "Justice  National Football League",
      "numberOfWords": 4,
      "numberOfLetters": 29
    },
    {
      "answer": "Kangaroo  Pencil Pouch",
      "numberOfWords": 3,
      "numberOfLetters": 19
    },
    {
      "answer": "Kathy  Dublin Ireland",
      "numberOfWords": 3,
      "numberOfLetters": 18
    },
    {
      "answer": "Kerry  Seattle Washington",
      "numberOfWords": 3,
      "numberOfLetters": 22
    },
    {
      "answer": "Kevin  Crispy Bacon",
      "numberOfWords": 3,
      "numberOfLetters": 16
    },
    {
      "answer": "Kevin  Will Smith",
      "numberOfWords": 3,
      "numberOfLetters": 14
    },
    {
      "answer": "Kids  Dollar Menu",
      "numberOfWords": 3,
      "numberOfLetters": 14
    },
    {
      "answer": "King  Double Room",
      "numberOfWords": 3,
      "numberOfLetters": 14
    },
    {
      "answer": "King  Norman Lear",
      "numberOfWords": 3,
      "numberOfLetters": 14
    },
    {
      "answer": "Kit  Swift Fox",
      "numberOfWords": 3,
      "numberOfLetters": 11
    },
    {
      "answer": "Knockout  Rum Punch",
      "numberOfWords": 3,
      "numberOfLetters": 16
    },
    {
      "answer": "Kuiper  Leather Belt",
      "numberOfWords": 3,
      "numberOfLetters": 17
    },
    {
      "answer": "Lab  Life Partner",
      "numberOfWords": 3,
      "numberOfLetters": 14
    },
    {
      "answer": "Larry  Big Bird",
      "numberOfWords": 3,
      "numberOfLetters": 12
    },
    {
      "answer": "Las Vegas  Bug Strip",
      "numberOfWords": 4,
      "numberOfLetters": 16
    },
    {
      "answer": "Late And Swing Shift",
      "numberOfWords": 4,
      "numberOfLetters": 17
    },
    {
      "answer": "Leather  Book Jacket",
      "numberOfWords": 3,
      "numberOfLetters": 17
    },
    {
      "answer": "Leather  Yellow Jacket",
      "numberOfWords": 3,
      "numberOfLetters": 19
    },
    {
      "answer": "Leather And Book Jacket",
      "numberOfWords": 4,
      "numberOfLetters": 20
    },
    {
      "answer": "Legislative  Tree Branch",
      "numberOfWords": 3,
      "numberOfLetters": 21
    },
    {
      "answer": "Lemon  Cough Drops",
      "numberOfWords": 3,
      "numberOfLetters": 15
    },
    {
      "answer": "Letter  Book Jacket",
      "numberOfWords": 3,
      "numberOfLetters": 16
    },
    {
      "answer": "Lettuce  Thats A Wrap",
      "numberOfWords": 4,
      "numberOfLetters": 17
    },
    {
      "answer": "Lewis  Jack Black",
      "numberOfWords": 3,
      "numberOfLetters": 14
    },
    {
      "answer": "Lights Camera  Affirmative Action",
      "numberOfWords": 4,
      "numberOfLetters": 29
    },
    {
      "answer": "Liquid  Clean Air",
      "numberOfWords": 3,
      "numberOfLetters": 14
    },
    {
      "answer": "Liquor  Kitchen Cabinet",
      "numberOfWords": 3,
      "numberOfLetters": 20
    },
    {
      "answer": "Little Red Riding  Robin Hood",
      "numberOfWords": 5,
      "numberOfLetters": 24
    },
    {
      "answer": "Live And In Concert",
      "numberOfWords": 4,
      "numberOfLetters": 16
    },
    {
      "answer": "Live On  First Love",
      "numberOfWords": 4,
      "numberOfLetters": 15
    },
    {
      "answer": "Loan  Police Officer",
      "numberOfWords": 3,
      "numberOfLetters": 17
    },
    {
      "answer": "Location  Girl Scout",
      "numberOfWords": 3,
      "numberOfLetters": 17
    },
    {
      "answer": "Lois  Country Lane",
      "numberOfWords": 3,
      "numberOfLetters": 15
    },
    {
      "answer": "Lois  Memory Lane",
      "numberOfWords": 3,
      "numberOfLetters": 14
    },
    {
      "answer": "Long Grain  Wild Rice",
      "numberOfWords": 4,
      "numberOfLetters": 17
    },
    {
      "answer": "Lost  State Highway",
      "numberOfWords": 3,
      "numberOfLetters": 16
    },
    {
      "answer": "Love  Bike Handles",
      "numberOfWords": 3,
      "numberOfLetters": 15
    },
    {
      "answer": "Love Me  Legal Tender",
      "numberOfWords": 4,
      "numberOfLetters": 17
    },
    {
      "answer": "Lower  Upper Bunk",
      "numberOfWords": 3,
      "numberOfLetters": 14
    },
    {
      "answer": "Lucille  Beach Ball",
      "numberOfWords": 3,
      "numberOfLetters": 16
    },
    {
      "answer": "Lucille  Rubber Ball",
      "numberOfWords": 3,
      "numberOfLetters": 17
    },
    {
      "answer": "Lucky  Copper Penny",
      "numberOfWords": 3,
      "numberOfLetters": 16
    },
    {
      "answer": "Luke  Animal Cage",
      "numberOfWords": 3,
      "numberOfLetters": 14
    },
    {
      "answer": "Luke  Chris Evans",
      "numberOfWords": 3,
      "numberOfLetters": 14
    },
    {
      "answer": "Luke And Chris Evans",
      "numberOfWords": 4,
      "numberOfLetters": 17
    },
    {
      "answer": "Lunch  Milk Money",
      "numberOfWords": 3,
      "numberOfLetters": 14
    },
    {
      "answer": "Lunch  Red Wagon",
      "numberOfWords": 3,
      "numberOfLetters": 13
    },
    {
      "answer": "Luxury Chrysler Sedan",
      "numberOfWords": 3,
      "numberOfLetters": 19
    },
    {
      "answer": "Macintosh  The Big Apple",
      "numberOfWords": 4,
      "numberOfLetters": 20
    },
    {
      "answer": "Madison Square  Rose Garden",
      "numberOfWords": 4,
      "numberOfLetters": 23
    },
    {
      "answer": "Mae  Wild West",
      "numberOfWords": 3,
      "numberOfLetters": 11
    },
    {
      "answer": "Magic  Cold Spell",
      "numberOfWords": 3,
      "numberOfLetters": 14
    },
    {
      "answer": "Magic And Cold Spell",
      "numberOfWords": 4,
      "numberOfLetters": 17
    },
    {
      "answer": "Magical And Flower Power",
      "numberOfWords": 4,
      "numberOfLetters": 21
    },
    {
      "answer": "Magical And Purchasing Power",
      "numberOfWords": 4,
      "numberOfLetters": 25
    },
    {
      "answer": "Magical And Solar Power",
      "numberOfWords": 4,
      "numberOfLetters": 20
    },
    {
      "answer": "Magical And Wind Power",
      "numberOfWords": 4,
      "numberOfLetters": 19
    },
    {
      "answer": "Magical And World Power",
      "numberOfWords": 4,
      "numberOfLetters": 20
    },
    {
      "answer": "Magnetic  Baseball Field",
      "numberOfWords": 3,
      "numberOfLetters": 21
    },
    {
      "answer": "Magnetic  Football Field",
      "numberOfWords": 3,
      "numberOfLetters": 21
    },
    {
      "answer": "Main  Golf Course",
      "numberOfWords": 3,
      "numberOfLetters": 14
    },
    {
      "answer": "Main  Lunch Menu",
      "numberOfWords": 3,
      "numberOfLetters": 13
    },
    {
      "answer": "Makeup  Emergency Kit",
      "numberOfWords": 3,
      "numberOfLetters": 18
    },
    {
      "answer": "Mandarin  Navel Oranges",
      "numberOfWords": 3,
      "numberOfLetters": 20
    },
    {
      "answer": "Map  Musk Turtle",
      "numberOfWords": 3,
      "numberOfLetters": 13
    },
    {
      "answer": "Marching And Rubber Band",
      "numberOfWords": 4,
      "numberOfLetters": 21
    },
    {
      "answer": "Marine  Green Iguana",
      "numberOfWords": 3,
      "numberOfLetters": 17
    },
    {
      "answer": "Marine And Green Iguana",
      "numberOfWords": 4,
      "numberOfLetters": 20
    },
    {
      "answer": "Mark  Shania Twain",
      "numberOfWords": 3,
      "numberOfLetters": 15
    },
    {
      "answer": "Market  Sticker Price",
      "numberOfWords": 3,
      "numberOfLetters": 18
    },
    {
      "answer": "Mashed  Small Potatoes",
      "numberOfWords": 3,
      "numberOfLetters": 19
    },
    {
      "answer": "Massage  Beauty Parlor",
      "numberOfWords": 3,
      "numberOfLetters": 19
    },
    {
      "answer": "Massage  Olive Oil",
      "numberOfWords": 3,
      "numberOfLetters": 15
    },
    {
      "answer": "Massage And Beauty Parlor",
      "numberOfWords": 4,
      "numberOfLetters": 22
    },
    {
      "answer": "Matinee  American Idol",
      "numberOfWords": 3,
      "numberOfLetters": 19
    },
    {
      "answer": "Matthew  Katy Perry",
      "numberOfWords": 3,
      "numberOfLetters": 16
    },
    {
      "answer": "Max  WindChill Factor",
      "numberOfWords": 3,
      "numberOfLetters": 18
    },
    {
      "answer": "Memory  ThankYou Card",
      "numberOfWords": 3,
      "numberOfLetters": 18
    },
    {
      "answer": "Mentally  Medical Alert",
      "numberOfWords": 3,
      "numberOfLetters": 20
    },
    {
      "answer": "Mesolithic  Neolithic Era",
      "numberOfWords": 3,
      "numberOfLetters": 22
    },
    {
      "answer": "Meteor  Cold Shower",
      "numberOfWords": 3,
      "numberOfLetters": 16
    },
    {
      "answer": "Meteor  Hot Shower",
      "numberOfWords": 3,
      "numberOfLetters": 15
    },
    {
      "answer": "Meteor  Warm Shower",
      "numberOfWords": 3,
      "numberOfLetters": 16
    },
    {
      "answer": "Meteor And Cold Shower",
      "numberOfWords": 4,
      "numberOfLetters": 19
    },
    {
      "answer": "Michael  Diane Keaton",
      "numberOfWords": 3,
      "numberOfLetters": 18
    },
    {
      "answer": "Mickey  Fireplace Mantle",
      "numberOfWords": 3,
      "numberOfLetters": 21
    },
    {
      "answer": "Microsoft  DriveThru Windows",
      "numberOfWords": 3,
      "numberOfLetters": 25
    },
    {
      "answer": "Middle  Though The Ages",
      "numberOfWords": 4,
      "numberOfLetters": 19
    },
    {
      "answer": "Middle  Through The Ages",
      "numberOfWords": 4,
      "numberOfLetters": 20
    },
    {
      "answer": "Mile  Magic Marker",
      "numberOfWords": 3,
      "numberOfLetters": 15
    },
    {
      "answer": "Military  Charging Base",
      "numberOfWords": 3,
      "numberOfLetters": 20
    },
    {
      "answer": "Military  First Base",
      "numberOfWords": 3,
      "numberOfLetters": 17
    },
    {
      "answer": "Milk  Baby Powder",
      "numberOfWords": 3,
      "numberOfLetters": 14
    },
    {
      "answer": "Minnesota  Fraternal Twins",
      "numberOfWords": 3,
      "numberOfLetters": 23
    },
    {
      "answer": "Money  Leather Belt",
      "numberOfWords": 3,
      "numberOfLetters": 16
    },
    {
      "answer": "Monkey  Chocolate Bars",
      "numberOfWords": 3,
      "numberOfLetters": 19
    },
    {
      "answer": "Morning  Mountain Dew",
      "numberOfWords": 3,
      "numberOfLetters": 18
    },
    {
      "answer": "Morse  Source Code",
      "numberOfWords": 3,
      "numberOfLetters": 15
    },
    {
      "answer": "Mother  Canadian Goose",
      "numberOfWords": 3,
      "numberOfLetters": 19
    },
    {
      "answer": "Mother  Duck Duck Goose",
      "numberOfWords": 4,
      "numberOfLetters": 19
    },
    {
      "answer": "Mother And Canadian Goose",
      "numberOfWords": 4,
      "numberOfLetters": 22
    },
    {
      "answer": "Motor  Olive Oil",
      "numberOfWords": 3,
      "numberOfLetters": 13
    },
    {
      "answer": "Movie  Chip Clip",
      "numberOfWords": 3,
      "numberOfLetters": 13
    },
    {
      "answer": "Movie  Toy Train Set",
      "numberOfWords": 4,
      "numberOfLetters": 16
    },
    {
      "answer": "Music  Capital City",
      "numberOfWords": 3,
      "numberOfLetters": 16
    },
    {
      "answer": "Music City  Rising Star",
      "numberOfWords": 4,
      "numberOfLetters": 19
    },
    {
      "answer": "Musical  Winning Score",
      "numberOfWords": 3,
      "numberOfLetters": 19
    },
    {
      "answer": "Musical And Love Notes",
      "numberOfWords": 4,
      "numberOfLetters": 19
    },
    {
      "answer": "Nasal  Secret Passage",
      "numberOfWords": 3,
      "numberOfLetters": 18
    },
    {
      "answer": "Nashville  Snake Venom",
      "numberOfWords": 3,
      "numberOfLetters": 19
    },
    {
      "answer": "Native  Pizza Hut",
      "numberOfWords": 3,
      "numberOfLetters": 14
    },
    {
      "answer": "Nature  Eerie Sounds",
      "numberOfWords": 3,
      "numberOfLetters": 17
    },
    {
      "answer": "Neal  Simple Simon",
      "numberOfWords": 3,
      "numberOfLetters": 15
    },
    {
      "answer": "Neil  Simple Simon",
      "numberOfWords": 3,
      "numberOfLetters": 15
    },
    {
      "answer": "Neil And Simple Simon",
      "numberOfWords": 4,
      "numberOfLetters": 18
    },
    {
      "answer": "Neon  Peace Sign",
      "numberOfWords": 3,
      "numberOfLetters": 13
    },
    {
      "answer": "Nervous  Computer System",
      "numberOfWords": 3,
      "numberOfLetters": 21
    },
    {
      "answer": "Nervous And Nuns Habit",
      "numberOfWords": 4,
      "numberOfLetters": 19
    },
    {
      "answer": "New York  Jumbo Jets",
      "numberOfWords": 4,
      "numberOfLetters": 16
    },
    {
      "answer": "Newspaper  Lemonade Stand",
      "numberOfWords": 3,
      "numberOfLetters": 22
    },
    {
      "answer": "Newspaper  Spinal Column",
      "numberOfWords": 3,
      "numberOfLetters": 21
    },
    {
      "answer": "No Parking  Twilight Zone",
      "numberOfWords": 4,
      "numberOfLetters": 21
    },
    {
      "answer": "NoParking  Twilight Zone",
      "numberOfWords": 3,
      "numberOfLetters": 21
    },
    {
      "answer": "Oak  Maple Trees",
      "numberOfWords": 3,
      "numberOfLetters": 13
    },
    {
      "answer": "Observation  Television Tower",
      "numberOfWords": 3,
      "numberOfLetters": 26
    },
    {
      "answer": "Obtuse  Acute Angle",
      "numberOfWords": 3,
      "numberOfLetters": 16
    },
    {
      "answer": "Ocean  First Floor",
      "numberOfWords": 3,
      "numberOfLetters": 15
    },
    {
      "answer": "Ode To Billie  Average Joe",
      "numberOfWords": 5,
      "numberOfLetters": 21
    },
    {
      "answer": "Ode To Billie And Average Joe",
      "numberOfWords": 6,
      "numberOfLetters": 24
    },
    {
      "answer": "Old  New Testament",
      "numberOfWords": 3,
      "numberOfLetters": 15
    },
    {
      "answer": "Ominous  Peace Sign",
      "numberOfWords": 3,
      "numberOfLetters": 16
    },
    {
      "answer": "One Flew Over The Cuckoos  Birds Nest",
      "numberOfWords": 7,
      "numberOfLetters": 30
    },
    {
      "answer": "Onion  Boxing Ring",
      "numberOfWords": 3,
      "numberOfLetters": 15
    },
    {
      "answer": "Orbital  Bike Path",
      "numberOfWords": 3,
      "numberOfLetters": 15
    },
    {
      "answer": "Orchestra  Peach Pit",
      "numberOfWords": 3,
      "numberOfLetters": 17
    },
    {
      "answer": "Orchestra And Peach Pit",
      "numberOfWords": 4,
      "numberOfLetters": 20
    },
    {
      "answer": "Orlando  Early Bloom",
      "numberOfWords": 3,
      "numberOfLetters": 17
    },
    {
      "answer": "Orlando  Full Bloom",
      "numberOfWords": 3,
      "numberOfLetters": 16
    },
    {
      "answer": "Outer  Limited Space",
      "numberOfWords": 3,
      "numberOfLetters": 17
    },
    {
      "answer": "Oxygen  Army Tank",
      "numberOfWords": 3,
      "numberOfLetters": 14
    },
    {
      "answer": "Oxygen  Think Tank",
      "numberOfWords": 3,
      "numberOfLetters": 15
    },
    {
      "answer": "Oxygen And Dunk Tank",
      "numberOfWords": 4,
      "numberOfLetters": 17
    },
    {
      "answer": "Oyster  David Rockerfeller",
      "numberOfWords": 3,
      "numberOfLetters": 23
    },
    {
      "answer": "Oysters  David Rockefeller",
      "numberOfWords": 3,
      "numberOfLetters": 23
    },
    {
      "answer": "Pacific  Towering Heights",
      "numberOfWords": 3,
      "numberOfLetters": 22
    },
    {
      "answer": "Pacific And Towering Heights",
      "numberOfWords": 4,
      "numberOfLetters": 25
    },
    {
      "answer": "Pacific Towering Hieghts",
      "numberOfWords": 3,
      "numberOfLetters": 22
    },
    {
      "answer": "Panama  Grand Canal",
      "numberOfWords": 3,
      "numberOfLetters": 16
    },
    {
      "answer": "Pandoras  Cardboard Box",
      "numberOfWords": 3,
      "numberOfLetters": 20
    },
    {
      "answer": "Papyrus  Leatherwork Sandal",
      "numberOfWords": 3,
      "numberOfLetters": 24
    },
    {
      "answer": "Papyrus  Leatherwork Sandals",
      "numberOfWords": 3,
      "numberOfLetters": 25
    },
    {
      "answer": "Parade  Root Beer Float",
      "numberOfWords": 4,
      "numberOfLetters": 19
    },
    {
      "answer": "Parade A Root Beer Float",
      "numberOfWords": 5,
      "numberOfLetters": 20
    },
    {
      "answer": "Parallel And County Lines",
      "numberOfWords": 4,
      "numberOfLetters": 22
    },
    {
      "answer": "Parcel  Guard Post",
      "numberOfWords": 3,
      "numberOfLetters": 15
    },
    {
      "answer": "Parsley  Corn Flakes",
      "numberOfWords": 3,
      "numberOfLetters": 17
    },
    {
      "answer": "Past  Future Tense",
      "numberOfWords": 3,
      "numberOfLetters": 15
    },
    {
      "answer": "Patent Leather  Bowling Shoes",
      "numberOfWords": 4,
      "numberOfLetters": 25
    },
    {
      "answer": "Patent Leather And Bowling Shoes",
      "numberOfWords": 5,
      "numberOfLetters": 28
    },
    {
      "answer": "Peach  Money Pit",
      "numberOfWords": 3,
      "numberOfLetters": 13
    },
    {
      "answer": "Peanut  Turtle Shell",
      "numberOfWords": 3,
      "numberOfLetters": 17
    },
    {
      "answer": "Peanut And Snail Shell",
      "numberOfWords": 4,
      "numberOfLetters": 19
    },
    {
      "answer": "Peanut Butter  Dixie Cups",
      "numberOfWords": 4,
      "numberOfLetters": 21
    },
    {
      "answer": "Peanut Butter  Dixiecups",
      "numberOfWords": 3,
      "numberOfLetters": 21
    },
    {
      "answer": "Peanut Butter And Dixie Cups",
      "numberOfWords": 5,
      "numberOfLetters": 24
    },
    {
      "answer": "Pecking  ToGo Order",
      "numberOfWords": 3,
      "numberOfLetters": 16
    },
    {
      "answer": "Pepper  Dandruff Flakes",
      "numberOfWords": 3,
      "numberOfLetters": 20
    },
    {
      "answer": "Pepper  Paper Mill",
      "numberOfWords": 3,
      "numberOfLetters": 15
    },
    {
      "answer": "Peppermint  Tree Bark",
      "numberOfWords": 3,
      "numberOfLetters": 18
    },
    {
      "answer": "Perfect  Boxing Match",
      "numberOfWords": 3,
      "numberOfLetters": 18
    },
    {
      "answer": "Personal  Wedding Planner",
      "numberOfWords": 3,
      "numberOfLetters": 22
    },
    {
      "answer": "Peter  Frying Pan",
      "numberOfWords": 3,
      "numberOfLetters": 14
    },
    {
      "answer": "Phone  Family Tree",
      "numberOfWords": 3,
      "numberOfLetters": 15
    },
    {
      "answer": "Piano  Park Bench",
      "numberOfWords": 3,
      "numberOfLetters": 14
    },
    {
      "answer": "Piggy And World Banks",
      "numberOfWords": 4,
      "numberOfLetters": 18
    },
    {
      "answer": "Pineapple  Mood Rings",
      "numberOfWords": 3,
      "numberOfLetters": 18
    },
    {
      "answer": "Pinto  Green Beans",
      "numberOfWords": 3,
      "numberOfLetters": 15
    },
    {
      "answer": "Pioneer  Winning Spirit",
      "numberOfWords": 3,
      "numberOfLetters": 20
    },
    {
      "answer": "Pit  Cleanup Crew",
      "numberOfWords": 3,
      "numberOfLetters": 14
    },
    {
      "answer": "Pittsburgh  Emperor Penguins",
      "numberOfWords": 3,
      "numberOfLetters": 25
    },
    {
      "answer": "Pizza  Earths Crust",
      "numberOfWords": 3,
      "numberOfLetters": 16
    },
    {
      "answer": "Pizza  Massage Parlor",
      "numberOfWords": 3,
      "numberOfLetters": 18
    },
    {
      "answer": "Pizza And Massage Parlor",
      "numberOfWords": 4,
      "numberOfLetters": 21
    },
    {
      "answer": "Poetic  Chief Justice",
      "numberOfWords": 3,
      "numberOfLetters": 18
    },
    {
      "answer": "Point  Security Guard",
      "numberOfWords": 3,
      "numberOfLetters": 18
    },
    {
      "answer": "Pole  Bank Vault",
      "numberOfWords": 3,
      "numberOfLetters": 13
    },
    {
      "answer": "Police  Court Officer",
      "numberOfWords": 3,
      "numberOfLetters": 18
    },
    {
      "answer": "Police  Lucky Dog",
      "numberOfWords": 3,
      "numberOfLetters": 14
    },
    {
      "answer": "Police  Wolf Whistle",
      "numberOfWords": 3,
      "numberOfLetters": 17
    },
    {
      "answer": "Political  Search Party",
      "numberOfWords": 3,
      "numberOfLetters": 20
    },
    {
      "answer": "Popcorn  Belle Of The Ball",
      "numberOfWords": 5,
      "numberOfLetters": 21
    },
    {
      "answer": "Popsicle  Pogo Stick",
      "numberOfWords": 3,
      "numberOfLetters": 17
    },
    {
      "answer": "Potato  Gps Chip",
      "numberOfWords": 3,
      "numberOfLetters": 13
    },
    {
      "answer": "Potted  Power Plant",
      "numberOfWords": 3,
      "numberOfLetters": 16
    },
    {
      "answer": "Power  News Outlet",
      "numberOfWords": 3,
      "numberOfLetters": 15
    },
    {
      "answer": "Power  Rubber Plant",
      "numberOfWords": 3,
      "numberOfLetters": 16
    },
    {
      "answer": "Power And Credible Source",
      "numberOfWords": 4,
      "numberOfLetters": 22
    },
    {
      "answer": "Power And News Outlet",
      "numberOfWords": 4,
      "numberOfLetters": 18
    },
    {
      "answer": "Presidential  Kitchen Cabinet",
      "numberOfWords": 3,
      "numberOfLetters": 26
    },
    {
      "answer": "Presidential  Navy Seal",
      "numberOfWords": 3,
      "numberOfLetters": 20
    },
    {
      "answer": "Pretty Perennial Plants",
      "numberOfWords": 3,
      "numberOfLetters": 21
    },
    {
      "answer": "Protein  Flash Powder",
      "numberOfWords": 3,
      "numberOfLetters": 18
    },
    {
      "answer": "Pumpkin  Dry Patch",
      "numberOfWords": 3,
      "numberOfLetters": 15
    },
    {
      "answer": "Punching  Tote Bag",
      "numberOfWords": 3,
      "numberOfLetters": 15
    },
    {
      "answer": "Radio  Ocean Waves",
      "numberOfWords": 3,
      "numberOfLetters": 15
    },
    {
      "answer": "Raiders Of The Lost  Noahs Ark",
      "numberOfWords": 6,
      "numberOfLetters": 24
    },
    {
      "answer": "Rat  Ice Pack",
      "numberOfWords": 3,
      "numberOfLetters": 10
    },
    {
      "answer": "Ray  Prince Charles",
      "numberOfWords": 3,
      "numberOfLetters": 16
    },
    {
      "answer": "Real Estate And Photo Developer",
      "numberOfWords": 5,
      "numberOfLetters": 27
    },
    {
      "answer": "Reality  Personal Check",
      "numberOfWords": 3,
      "numberOfLetters": 20
    },
    {
      "answer": "Record  Mailing Label",
      "numberOfWords": 3,
      "numberOfLetters": 18
    },
    {
      "answer": "Record  Soup Label",
      "numberOfWords": 3,
      "numberOfLetters": 15
    },
    {
      "answer": "Record And Soup Label",
      "numberOfWords": 4,
      "numberOfLetters": 18
    },
    {
      "answer": "Reflecting  Wading Pool",
      "numberOfWords": 3,
      "numberOfLetters": 20
    },
    {
      "answer": "Restaurant  Supermarket Chain",
      "numberOfWords": 3,
      "numberOfLetters": 26
    },
    {
      "answer": "Retail And Monkey Business",
      "numberOfWords": 4,
      "numberOfLetters": 23
    },
    {
      "answer": "Rice  Barley Kasha",
      "numberOfWords": 3,
      "numberOfLetters": 15
    },
    {
      "answer": "Rick  Shirley Jones",
      "numberOfWords": 3,
      "numberOfLetters": 16
    },
    {
      "answer": "Riverfront  National Park",
      "numberOfWords": 3,
      "numberOfLetters": 22
    },
    {
      "answer": "Roasting  Flash In The Pan",
      "numberOfWords": 5,
      "numberOfLetters": 21
    },
    {
      "answer": "Robin  Car Hood",
      "numberOfWords": 3,
      "numberOfLetters": 12
    },
    {
      "answer": "Rodeo  Midnight Cowboy",
      "numberOfWords": 3,
      "numberOfLetters": 19
    },
    {
      "answer": "Roller And Kentucky Derby",
      "numberOfWords": 4,
      "numberOfLetters": 22
    },
    {
      "answer": "Roman  Paid Holiday",
      "numberOfWords": 3,
      "numberOfLetters": 16
    },
    {
      "answer": "Roman  Public Forum",
      "numberOfWords": 3,
      "numberOfLetters": 16
    },
    {
      "answer": "Root  Erie Canal",
      "numberOfWords": 3,
      "numberOfLetters": 13
    },
    {
      "answer": "Root Beer  Parade Float",
      "numberOfWords": 4,
      "numberOfLetters": 19
    },
    {
      "answer": "Rough  Cold Draft",
      "numberOfWords": 3,
      "numberOfLetters": 14
    },
    {
      "answer": "Rubber  Pacific Ground Boa",
      "numberOfWords": 4,
      "numberOfLetters": 22
    },
    {
      "answer": "Rubber  Traveling Band",
      "numberOfWords": 3,
      "numberOfLetters": 19
    },
    {
      "answer": "Run  Pass Block",
      "numberOfWords": 3,
      "numberOfLetters": 12
    },
    {
      "answer": "Safety  Bowling Pin",
      "numberOfWords": 3,
      "numberOfLetters": 16
    },
    {
      "answer": "Salad  Super Bowl",
      "numberOfWords": 3,
      "numberOfLetters": 14
    },
    {
      "answer": "Salary  Baseball Cap",
      "numberOfWords": 3,
      "numberOfLetters": 17
    },
    {
      "answer": "Sally  Sunflower Field",
      "numberOfWords": 3,
      "numberOfLetters": 19
    },
    {
      "answer": "Sausage  Peppermint Patties",
      "numberOfWords": 3,
      "numberOfLetters": 24
    },
    {
      "answer": "Sausage  Web Link",
      "numberOfWords": 3,
      "numberOfLetters": 14
    },
    {
      "answer": "Science  Job Fair",
      "numberOfWords": 3,
      "numberOfLetters": 14
    },
    {
      "answer": "Scientific  Male Model",
      "numberOfWords": 3,
      "numberOfLetters": 19
    },
    {
      "answer": "Seattle  Denzil Washington",
      "numberOfWords": 3,
      "numberOfLetters": 23
    },
    {
      "answer": "Second  Mother Nature",
      "numberOfWords": 3,
      "numberOfLetters": 18
    },
    {
      "answer": "Senate  Title Page",
      "numberOfWords": 3,
      "numberOfLetters": 15
    },
    {
      "answer": "Sensational Seasonal Snacks",
      "numberOfWords": 3,
      "numberOfLetters": 25
    },
    {
      "answer": "Septic  Army Tank",
      "numberOfWords": 3,
      "numberOfLetters": 14
    },
    {
      "answer": "Sesame  Easy Street",
      "numberOfWords": 3,
      "numberOfLetters": 16
    },
    {
      "answer": "Sesame And Easy Street",
      "numberOfWords": 4,
      "numberOfLetters": 19
    },
    {
      "answer": "Shampoo  Punch Bowl",
      "numberOfWords": 3,
      "numberOfLetters": 16
    },
    {
      "answer": "Shania  Mark Twain",
      "numberOfWords": 3,
      "numberOfLetters": 15
    },
    {
      "answer": "Shea  Honey Butter",
      "numberOfWords": 3,
      "numberOfLetters": 15
    },
    {
      "answer": "Sheryl  Eating Crow",
      "numberOfWords": 3,
      "numberOfLetters": 16
    },
    {
      "answer": "Ships  Popcorn Hull",
      "numberOfWords": 3,
      "numberOfLetters": 16
    },
    {
      "answer": "Shipping  Carpool Lane",
      "numberOfWords": 3,
      "numberOfLetters": 19
    },
    {
      "answer": "Ships  College Course",
      "numberOfWords": 3,
      "numberOfLetters": 18
    },
    {
      "answer": "Ships  Colleges Course",
      "numberOfWords": 3,
      "numberOfLetters": 19
    },
    {
      "answer": "Shirley  Angus T Jones",
      "numberOfWords": 4,
      "numberOfLetters": 18
    },
    {
      "answer": "Shoe  Furniture Polish",
      "numberOfWords": 3,
      "numberOfLetters": 19
    },
    {
      "answer": "Shooting  Home On The Range",
      "numberOfWords": 5,
      "numberOfLetters": 22
    },
    {
      "answer": "Shooting  Movie Star",
      "numberOfWords": 3,
      "numberOfLetters": 17
    },
    {
      "answer": "Shopping  Carpool Lane",
      "numberOfWords": 3,
      "numberOfLetters": 19
    },
    {
      "answer": "Shower  Golf Caddy",
      "numberOfWords": 3,
      "numberOfLetters": 15
    },
    {
      "answer": "Shrimp  White Toast",
      "numberOfWords": 3,
      "numberOfLetters": 16
    },
    {
      "answer": "Siberian  Detroit Tigers",
      "numberOfWords": 3,
      "numberOfLetters": 21
    },
    {
      "answer": "Silicon  Tortilla Chip",
      "numberOfWords": 3,
      "numberOfLetters": 19
    },
    {
      "answer": "Silly Shenanigans",
      "numberOfWords": 2,
      "numberOfLetters": 16
    },
    {
      "answer": "Sin  Key To The City",
      "numberOfWords": 5,
      "numberOfLetters": 15
    },
    {
      "answer": "Sixteen  Birthday Candles",
      "numberOfWords": 3,
      "numberOfLetters": 22
    },
    {
      "answer": "Sloth  Sun Bear",
      "numberOfWords": 3,
      "numberOfLetters": 12
    },
    {
      "answer": "Smooth  Soft Texture",
      "numberOfWords": 3,
      "numberOfLetters": 17
    },
    {
      "answer": "Snowball And Celebrated Fight",
      "numberOfWords": 4,
      "numberOfLetters": 26
    },
    {
      "answer": "Solar  Celebrity Panel",
      "numberOfWords": 3,
      "numberOfLetters": 19
    },
    {
      "answer": "Solar  Control Panel",
      "numberOfWords": 3,
      "numberOfLetters": 17
    },
    {
      "answer": "Solar  Expert Panel",
      "numberOfWords": 3,
      "numberOfLetters": 16
    },
    {
      "answer": "Solar And Celebrity Panel",
      "numberOfWords": 4,
      "numberOfLetters": 22
    },
    {
      "answer": "Sonic  Baby Boom",
      "numberOfWords": 3,
      "numberOfLetters": 13
    },
    {
      "answer": "Sound  Side Effects",
      "numberOfWords": 3,
      "numberOfLetters": 16
    },
    {
      "answer": "Source  Dress Code",
      "numberOfWords": 3,
      "numberOfLetters": 15
    },
    {
      "answer": "South  National Park",
      "numberOfWords": 3,
      "numberOfLetters": 17
    },
    {
      "answer": "Space  Regularly Scheduled Program",
      "numberOfWords": 4,
      "numberOfLetters": 30
    },
    {
      "answer": "Space  Regularly Scheduled Programs",
      "numberOfWords": 4,
      "numberOfLetters": 31
    },
    {
      "answer": "Space  TimeRelease Capsule",
      "numberOfWords": 3,
      "numberOfLetters": 23
    },
    {
      "answer": "Spanish Soft Steps",
      "numberOfWords": 3,
      "numberOfLetters": 16
    },
    {
      "answer": "Speech  Test Pattern",
      "numberOfWords": 3,
      "numberOfLetters": 17
    },
    {
      "answer": "Spelling  Busy Bee",
      "numberOfWords": 3,
      "numberOfLetters": 15
    },
    {
      "answer": "Spelling  Queen Bee",
      "numberOfWords": 3,
      "numberOfLetters": 16
    },
    {
      "answer": "Spelling  Queen Bees",
      "numberOfWords": 3,
      "numberOfLetters": 17
    },
    {
      "answer": "Spider And World Wide Web",
      "numberOfWords": 5,
      "numberOfLetters": 21
    },
    {
      "answer": "Spoiled  Army Brat",
      "numberOfWords": 3,
      "numberOfLetters": 15
    },
    {
      "answer": "Sports  Candy Bar",
      "numberOfWords": 3,
      "numberOfLetters": 14
    },
    {
      "answer": "Sports  Concert Arena",
      "numberOfWords": 3,
      "numberOfLetters": 18
    },
    {
      "answer": "Spring  High Fever",
      "numberOfWords": 3,
      "numberOfLetters": 15
    },
    {
      "answer": "Sprinkler  Solar System",
      "numberOfWords": 3,
      "numberOfLetters": 20
    },
    {
      "answer": "Staff  Grocery List",
      "numberOfWords": 3,
      "numberOfLetters": 16
    },
    {
      "answer": "Stage  Pit Crew",
      "numberOfWords": 3,
      "numberOfLetters": 12
    },
    {
      "answer": "Starboard  Final Bow",
      "numberOfWords": 3,
      "numberOfLetters": 17
    },
    {
      "answer": "Starboard And Final Bow",
      "numberOfWords": 4,
      "numberOfLetters": 20
    },
    {
      "answer": "Stars Stripes  States",
      "numberOfWords": 3,
      "numberOfLetters": 18
    },
    {
      "answer": "Starship  Golden Gate Bridge",
      "numberOfWords": 4,
      "numberOfLetters": 24
    },
    {
      "answer": "State  Red Flag",
      "numberOfWords": 3,
      "numberOfLetters": 12
    },
    {
      "answer": "State  Venture Capital",
      "numberOfWords": 3,
      "numberOfLetters": 19
    },
    {
      "answer": "States  Civil Rights",
      "numberOfWords": 3,
      "numberOfLetters": 17
    },
    {
      "answer": "Steam And Wiggle Room",
      "numberOfWords": 4,
      "numberOfLetters": 18
    },
    {
      "answer": "Stick  Late Shift",
      "numberOfWords": 3,
      "numberOfLetters": 14
    },
    {
      "answer": "Stock  Money Market",
      "numberOfWords": 3,
      "numberOfLetters": 16
    },
    {
      "answer": "Stock  Money Markets",
      "numberOfWords": 3,
      "numberOfLetters": 17
    },
    {
      "answer": "Stock  Waiters Tips",
      "numberOfWords": 3,
      "numberOfLetters": 16
    },
    {
      "answer": "Stone  New Age",
      "numberOfWords": 3,
      "numberOfLetters": 11
    },
    {
      "answer": "Stonewall And Kate Jackson",
      "numberOfWords": 4,
      "numberOfLetters": 23
    },
    {
      "answer": "Stop  Dollar Sign",
      "numberOfWords": 3,
      "numberOfLetters": 14
    },
    {
      "answer": "Storage  Family Unit",
      "numberOfWords": 3,
      "numberOfLetters": 17
    },
    {
      "answer": "Storm  Power Surge",
      "numberOfWords": 3,
      "numberOfLetters": 15
    },
    {
      "answer": "Strawberry  Humble Pie",
      "numberOfWords": 3,
      "numberOfLetters": 19
    },
    {
      "answer": "Strawberry  Pearl Jam",
      "numberOfWords": 3,
      "numberOfLetters": 18
    },
    {
      "answer": "Strawberry  Traffic Jam",
      "numberOfWords": 3,
      "numberOfLetters": 20
    },
    {
      "answer": "Strawberry And Pearl Jam",
      "numberOfWords": 4,
      "numberOfLetters": 21
    },
    {
      "answer": "Strikes Spares  Splits",
      "numberOfWords": 3,
      "numberOfLetters": 19
    },
    {
      "answer": "Student  Perfect Body",
      "numberOfWords": 3,
      "numberOfLetters": 18
    },
    {
      "answer": "Student And Perfect Body",
      "numberOfWords": 4,
      "numberOfLetters": 21
    },
    {
      "answer": "Stumbling  Building Block",
      "numberOfWords": 3,
      "numberOfLetters": 22
    },
    {
      "answer": "Stylish Shops  Restaurants",
      "numberOfWords": 3,
      "numberOfLetters": 23
    },
    {
      "answer": "Sucker  Fruit Punch",
      "numberOfWords": 3,
      "numberOfLetters": 16
    },
    {
      "answer": "Sugar  Ice Cubes",
      "numberOfWords": 3,
      "numberOfLetters": 13
    },
    {
      "answer": "Sugar  Rose Bowl",
      "numberOfWords": 3,
      "numberOfLetters": 13
    },
    {
      "answer": "Sulfur  City Blocks",
      "numberOfWords": 3,
      "numberOfLetters": 16
    },
    {
      "answer": "Summer  Beef Stock",
      "numberOfWords": 3,
      "numberOfLetters": 15
    },
    {
      "answer": "Summer  Winter Coat",
      "numberOfWords": 3,
      "numberOfLetters": 16
    },
    {
      "answer": "Sunflower  Pumpkin Seeds",
      "numberOfWords": 3,
      "numberOfLetters": 21
    },
    {
      "answer": "Sunset  A Bacon Strip",
      "numberOfWords": 4,
      "numberOfLetters": 17
    },
    {
      "answer": "Sunset  Bacon Strip",
      "numberOfWords": 3,
      "numberOfLetters": 16
    },
    {
      "answer": "Sunset And Bacon Strip",
      "numberOfWords": 4,
      "numberOfLetters": 19
    },
    {
      "answer": "Supreme  Traffic Court",
      "numberOfWords": 3,
      "numberOfLetters": 19
    },
    {
      "answer": "Supreme  Volleyball Court",
      "numberOfWords": 3,
      "numberOfLetters": 22
    },
    {
      "answer": "Surprise  Bridal Party",
      "numberOfWords": 3,
      "numberOfLetters": 19
    },
    {
      "answer": "Sweet  Wisdom Tooth",
      "numberOfWords": 3,
      "numberOfLetters": 16
    },
    {
      "answer": "Swim  Cedar Trunks",
      "numberOfWords": 3,
      "numberOfLetters": 15
    },
    {
      "answer": "Swim  Elephant Trunks",
      "numberOfWords": 3,
      "numberOfLetters": 18
    },
    {
      "answer": "Swim  Tree Trunks",
      "numberOfWords": 3,
      "numberOfLetters": 14
    },
    {
      "answer": "Swimming  A Baseball Cap",
      "numberOfWords": 4,
      "numberOfLetters": 20
    },
    {
      "answer": "Swimming  Baseball Cap",
      "numberOfWords": 3,
      "numberOfLetters": 19
    },
    {
      "answer": "Swimming  Reflecting Pool",
      "numberOfWords": 3,
      "numberOfLetters": 22
    },
    {
      "answer": "Swivel  Elbow Pads",
      "numberOfWords": 3,
      "numberOfLetters": 15
    },
    {
      "answer": "Taste  Best Buds",
      "numberOfWords": 3,
      "numberOfLetters": 13
    },
    {
      "answer": "Tater  Small Tot",
      "numberOfWords": 3,
      "numberOfLetters": 13
    },
    {
      "answer": "Tax  Bottle Refund",
      "numberOfWords": 3,
      "numberOfLetters": 15
    },
    {
      "answer": "Tax  Wall Bracket",
      "numberOfWords": 3,
      "numberOfLetters": 14
    },
    {
      "answer": "Telegraph  Steep Hill",
      "numberOfWords": 3,
      "numberOfLetters": 18
    },
    {
      "answer": "Telephone  Ski Poles",
      "numberOfWords": 3,
      "numberOfLetters": 17
    },
    {
      "answer": "Telephone  South Pole",
      "numberOfWords": 3,
      "numberOfLetters": 18
    },
    {
      "answer": "Television  Airline Pilot",
      "numberOfWords": 3,
      "numberOfLetters": 22
    },
    {
      "answer": "Television  English Channel",
      "numberOfWords": 3,
      "numberOfLetters": 24
    },
    {
      "answer": "Television  Party Host",
      "numberOfWords": 3,
      "numberOfLetters": 19
    },
    {
      "answer": "Television  Tourist Season",
      "numberOfWords": 3,
      "numberOfLetters": 23
    },
    {
      "answer": "Tennis And Inaugural Ball",
      "numberOfWords": 4,
      "numberOfLetters": 22
    },
    {
      "answer": "The Breakfast  Fitness Club",
      "numberOfWords": 4,
      "numberOfLetters": 23
    },
    {
      "answer": "The Breakfast And Fitness Club",
      "numberOfWords": 5,
      "numberOfLetters": 26
    },
    {
      "answer": "The Da Vinci  Area Code",
      "numberOfWords": 5,
      "numberOfLetters": 18
    },
    {
      "answer": "The French  Bad Connection",
      "numberOfWords": 4,
      "numberOfLetters": 22
    },
    {
      "answer": "The Great  Wash Basin",
      "numberOfWords": 4,
      "numberOfLetters": 17
    },
    {
      "answer": "The Great And The Wash Basin",
      "numberOfWords": 6,
      "numberOfLetters": 23
    },
    {
      "answer": "The Great And Wash Basin",
      "numberOfWords": 5,
      "numberOfLetters": 20
    },
    {
      "answer": "The National  Nose Guard",
      "numberOfWords": 4,
      "numberOfLetters": 20
    },
    {
      "answer": "The National And Nose Guard",
      "numberOfWords": 5,
      "numberOfLetters": 23
    },
    {
      "answer": "The Sixth  Common Sense",
      "numberOfWords": 4,
      "numberOfLetters": 19
    },
    {
      "answer": "The Washington  Scratching Post",
      "numberOfWords": 4,
      "numberOfLetters": 27
    },
    {
      "answer": "The Weather  English Channel",
      "numberOfWords": 4,
      "numberOfLetters": 24
    },
    {
      "answer": "The Wild  Brady Bunch",
      "numberOfWords": 4,
      "numberOfLetters": 17
    },
    {
      "answer": "The Wizard Of  Dr Oz",
      "numberOfWords": 5,
      "numberOfLetters": 15
    },
    {
      "answer": "Think  Water Tank",
      "numberOfWords": 3,
      "numberOfLetters": 14
    },
    {
      "answer": "Thomas  George Jefferson",
      "numberOfWords": 3,
      "numberOfLetters": 21
    },
    {
      "answer": "Thompson  Fraternal Twins",
      "numberOfWords": 3,
      "numberOfLetters": 22
    },
    {
      "answer": "Tidal  Permanent Wave",
      "numberOfWords": 3,
      "numberOfLetters": 18
    },
    {
      "answer": "Tie  Video Clip",
      "numberOfWords": 3,
      "numberOfLetters": 12
    },
    {
      "answer": "Tissue And Post Office Box",
      "numberOfWords": 5,
      "numberOfLetters": 22
    },
    {
      "answer": "TollFree  Lucky Number",
      "numberOfWords": 3,
      "numberOfLetters": 19
    },
    {
      "answer": "Tom And Diane Sawyer",
      "numberOfWords": 4,
      "numberOfLetters": 17
    },
    {
      "answer": "Total  Accountable Recall",
      "numberOfWords": 3,
      "numberOfLetters": 22
    },
    {
      "answer": "Total  Automobile Recall",
      "numberOfWords": 3,
      "numberOfLetters": 21
    },
    {
      "answer": "Traffic  Blueberry Jam",
      "numberOfWords": 3,
      "numberOfLetters": 19
    },
    {
      "answer": "Traffic  Raspberry Jam",
      "numberOfWords": 3,
      "numberOfLetters": 19
    },
    {
      "answer": "Traffic  Strawberry Jam",
      "numberOfWords": 3,
      "numberOfLetters": 20
    },
    {
      "answer": "Traffic And Blackberry Jam",
      "numberOfWords": 4,
      "numberOfLetters": 23
    },
    {
      "answer": "Train  Dog Whistle",
      "numberOfWords": 3,
      "numberOfLetters": 15
    },
    {
      "answer": "Train  Right On Track",
      "numberOfWords": 4,
      "numberOfLetters": 17
    },
    {
      "answer": "Trained  State Seal",
      "numberOfWords": 3,
      "numberOfLetters": 16
    },
    {
      "answer": "Travel  Generous Tips",
      "numberOfWords": 3,
      "numberOfLetters": 18
    },
    {
      "answer": "Travel  Gift Package",
      "numberOfWords": 3,
      "numberOfLetters": 17
    },
    {
      "answer": "Treasure And World Map",
      "numberOfWords": 4,
      "numberOfLetters": 19
    },
    {
      "answer": "Treble  Bass Clef",
      "numberOfWords": 3,
      "numberOfLetters": 14
    },
    {
      "answer": "Tree  Dog Bark",
      "numberOfWords": 3,
      "numberOfLetters": 11
    },
    {
      "answer": "Tropical  Temperate Zone",
      "numberOfWords": 3,
      "numberOfLetters": 21
    },
    {
      "answer": "Tulip  Light Bulb",
      "numberOfWords": 3,
      "numberOfLetters": 14
    },
    {
      "answer": "Twelve  Bowling Pins",
      "numberOfWords": 3,
      "numberOfLetters": 17
    },
    {
      "answer": "Twilight And Comfort Zone",
      "numberOfWords": 4,
      "numberOfLetters": 22
    },
    {
      "answer": "Twilight And Time Zone",
      "numberOfWords": 4,
      "numberOfLetters": 19
    },
    {
      "answer": "Tyler  Matthew Perry",
      "numberOfWords": 3,
      "numberOfLetters": 17
    },
    {
      "answer": "Typewriter  Hair Ribbon",
      "numberOfWords": 3,
      "numberOfLetters": 20
    },
    {
      "answer": "Tyra  Investment Banks",
      "numberOfWords": 3,
      "numberOfLetters": 19
    },
    {
      "answer": "Unanimous And Final Decision",
      "numberOfWords": 4,
      "numberOfLetters": 25
    },
    {
      "answer": "Undercover  Free Agent",
      "numberOfWords": 3,
      "numberOfLetters": 19
    },
    {
      "answer": "Upper  Lower Body",
      "numberOfWords": 3,
      "numberOfLetters": 14
    },
    {
      "answer": "Useless And Additional Information",
      "numberOfWords": 4,
      "numberOfLetters": 31
    },
    {
      "answer": "Vanna  Snow White",
      "numberOfWords": 3,
      "numberOfLetters": 14
    },
    {
      "answer": "Vantage  Whats Your Point",
      "numberOfWords": 4,
      "numberOfLetters": 21
    },
    {
      "answer": "Vantage  Whats Your Point",
      "numberOfWords": 4,
      "numberOfLetters": 21
    },
    {
      "answer": "Vapor  Traffic Cone",
      "numberOfWords": 3,
      "numberOfLetters": 16
    },
    {
      "answer": "Varsity  David Letterman",
      "numberOfWords": 3,
      "numberOfLetters": 21
    },
    {
      "answer": "Vegetable  Rough Patch",
      "numberOfWords": 3,
      "numberOfLetters": 19
    },
    {
      "answer": "Vending And Slot Machine",
      "numberOfWords": 4,
      "numberOfLetters": 21
    },
    {
      "answer": "Video  Mind Game",
      "numberOfWords": 3,
      "numberOfLetters": 13
    },
    {
      "answer": "Vincent  Worth The Price",
      "numberOfWords": 4,
      "numberOfLetters": 20
    },
    {
      "answer": "Vinyl  Public Record",
      "numberOfWords": 3,
      "numberOfLetters": 17
    },
    {
      "answer": "Vinyl  World Records",
      "numberOfWords": 3,
      "numberOfLetters": 17
    },
    {
      "answer": "Vinyl And Public Record",
      "numberOfWords": 4,
      "numberOfLetters": 20
    },
    {
      "answer": "Vip And Shopping List",
      "numberOfWords": 4,
      "numberOfLetters": 18
    },
    {
      "answer": "Volleyball  Butterfly Net",
      "numberOfWords": 3,
      "numberOfLetters": 22
    },
    {
      "answer": "Waffle  Safety Cone",
      "numberOfWords": 3,
      "numberOfLetters": 16
    },
    {
      "answer": "Wagon  Speeding Train",
      "numberOfWords": 3,
      "numberOfLetters": 18
    },
    {
      "answer": "Wait Your  Sharp Turn",
      "numberOfWords": 4,
      "numberOfLetters": 17
    },
    {
      "answer": "Walking  Sightseeing Tour",
      "numberOfWords": 3,
      "numberOfLetters": 22
    },
    {
      "answer": "Warning  Turn Signal",
      "numberOfWords": 3,
      "numberOfLetters": 17
    },
    {
      "answer": "Warren  Ned Beatty",
      "numberOfWords": 3,
      "numberOfLetters": 15
    },
    {
      "answer": "Water And Softball Pitcher",
      "numberOfWords": 4,
      "numberOfLetters": 23
    },
    {
      "answer": "Way Off  Military Base",
      "numberOfWords": 4,
      "numberOfLetters": 18
    },
    {
      "answer": "Wayne  Isaac Newton",
      "numberOfWords": 3,
      "numberOfLetters": 16
    },
    {
      "answer": "Wedding  Marching Band",
      "numberOfWords": 3,
      "numberOfLetters": 19
    },
    {
      "answer": "Wedding  Orbital Ring",
      "numberOfWords": 3,
      "numberOfLetters": 18
    },
    {
      "answer": "Wedding  Warm Reception",
      "numberOfWords": 3,
      "numberOfLetters": 20
    },
    {
      "answer": "Wedding And Daily Planner",
      "numberOfWords": 4,
      "numberOfLetters": 22
    },
    {
      "answer": "Welcome  Place Mat",
      "numberOfWords": 3,
      "numberOfLetters": 15
    },
    {
      "answer": "West  Chicken Wing",
      "numberOfWords": 3,
      "numberOfLetters": 15
    },
    {
      "answer": "Westward  Business Expansion",
      "numberOfWords": 3,
      "numberOfLetters": 25
    },
    {
      "answer": "Whole  Half Rest",
      "numberOfWords": 3,
      "numberOfLetters": 13
    },
    {
      "answer": "Whoopee  Sofa Cushion",
      "numberOfWords": 3,
      "numberOfLetters": 18
    },
    {
      "answer": "Whoopi  Bernard Goldberg",
      "numberOfWords": 3,
      "numberOfLetters": 21
    },
    {
      "answer": "Will  Granny Smith",
      "numberOfWords": 3,
      "numberOfLetters": 15
    },
    {
      "answer": "Window  Movie Screen",
      "numberOfWords": 3,
      "numberOfLetters": 17
    },
    {
      "answer": "Witches  IceCold Brew",
      "numberOfWords": 3,
      "numberOfLetters": 18
    },
    {
      "answer": "Witness  Lemonade Stand",
      "numberOfWords": 3,
      "numberOfLetters": 20
    },
    {
      "answer": "Witness  Umbrella Stand",
      "numberOfWords": 3,
      "numberOfLetters": 20
    },
    {
      "answer": "Wolfgang  Hockey Puck",
      "numberOfWords": 3,
      "numberOfLetters": 18
    },
    {
      "answer": "Working  Elite Class",
      "numberOfWords": 3,
      "numberOfLetters": 17
    },
    {
      "answer": "Working And Elite Class",
      "numberOfWords": 4,
      "numberOfLetters": 20
    },
    {
      "answer": "Wrinkle  Sour Cream",
      "numberOfWords": 3,
      "numberOfLetters": 16
    },
    {
      "answer": "Yoga  Movie Studio",
      "numberOfWords": 3,
      "numberOfLetters": 15
    },
    {
      "answer": "Yoga And Precarious Position",
      "numberOfWords": 4,
      "numberOfLetters": 25
    },
    {
      "answer": "You Silly  Christmas Goose",
      "numberOfWords": 4,
      "numberOfLetters": 22
    },
    {
      "answer": "Zip  Area Code",
      "numberOfWords": 3,
      "numberOfLetters": 11
    },
    {
      "answer": "Zz  Big Top",
      "numberOfWords": 3,
      "numberOfLetters": 8
    }
  ]
}
