{
  "name": "Title",
  "answers": [
    {
      "answer": "A Bend In The River",
      "numberOfWords": 5,
      "numberOfLetters": 15
    },
    {
      "answer": "A Bugs Life",
      "numberOfWords": 3,
      "numberOfLetters": 9
    },
    {
      "answer": "A Charlie Brown Thanksgiving",
      "numberOfWords": 4,
      "numberOfLetters": 25
    },
    {
      "answer": "A Chorus Line",
      "numberOfWords": 3,
      "numberOfLetters": 11
    },
    {
      "answer": "A Christmas Carol",
      "numberOfWords": 3,
      "numberOfLetters": 15
    },
    {
      "answer": "A Clash Of Kings",
      "numberOfWords": 4,
      "numberOfLetters": 13
    },
    {
      "answer": "A Clockwork Orange",
      "numberOfWords": 3,
      "numberOfLetters": 16
    },
    {
      "answer": "A Dance With Dragons",
      "numberOfWords": 4,
      "numberOfLetters": 17
    },
    {
      "answer": "A Friend Of The Earth",
      "numberOfWords": 5,
      "numberOfLetters": 17
    },
    {
      "answer": "A Great Buy",
      "numberOfWords": 3,
      "numberOfLetters": 9
    },
    {
      "answer": "A Little Life",
      "numberOfWords": 3,
      "numberOfLetters": 11
    },
    {
      "answer": "A Matter Of Gravity",
      "numberOfWords": 4,
      "numberOfLetters": 16
    },
    {
      "answer": "A Midsummer Nights Dream",
      "numberOfWords": 4,
      "numberOfLetters": 21
    },
    {
      "answer": "A Nice Hot Shower",
      "numberOfWords": 4,
      "numberOfLetters": 14
    },
    {
      "answer": "A Passage To India",
      "numberOfWords": 4,
      "numberOfLetters": 15
    },
    {
      "answer": "A Pat On The Back",
      "numberOfWords": 5,
      "numberOfLetters": 13
    },
    {
      "answer": "A Song Of Ice And Fire",
      "numberOfWords": 6,
      "numberOfLetters": 17
    },
    {
      "answer": "A Spool Of Blue Thread",
      "numberOfWords": 5,
      "numberOfLetters": 18
    },
    {
      "answer": "A Thousand Splendid Suns",
      "numberOfWords": 4,
      "numberOfLetters": 21
    },
    {
      "answer": "A Time Apart",
      "numberOfWords": 3,
      "numberOfLetters": 10
    },
    {
      "answer": "A Tree Grows In Brooklyn",
      "numberOfWords": 5,
      "numberOfLetters": 20
    },
    {
      "answer": "A Visit From St Nicholas",
      "numberOfWords": 5,
      "numberOfLetters": 20
    },
    {
      "answer": "A Wild Sheep Chase",
      "numberOfWords": 4,
      "numberOfLetters": 15
    },
    {
      "answer": "Aarp Magazine",
      "numberOfWords": 2,
      "numberOfLetters": 12
    },
    {
      "answer": "Abc Song",
      "numberOfWords": 2,
      "numberOfLetters": 7
    },
    {
      "answer": "Achievement In Excellence",
      "numberOfWords": 3,
      "numberOfLetters": 23
    },
    {
      "answer": "Airline Highway",
      "numberOfWords": 2,
      "numberOfLetters": 14
    },
    {
      "answer": "Aladdin",
      "numberOfWords": 1,
      "numberOfLetters": 7
    },
    {
      "answer": "Aladdin And The Wonderful Lamp",
      "numberOfWords": 5,
      "numberOfLetters": 26
    },
    {
      "answer": "Album Of The Year",
      "numberOfWords": 4,
      "numberOfLetters": 14
    },
    {
      "answer": "Alices Adventures In Wonderland",
      "numberOfWords": 4,
      "numberOfLetters": 28
    },
    {
      "answer": "All Quiet On The Western Front",
      "numberOfWords": 6,
      "numberOfLetters": 25
    },
    {
      "answer": "All That Jazz",
      "numberOfWords": 3,
      "numberOfLetters": 11
    },
    {
      "answer": "All The Birds In The Sky",
      "numberOfWords": 6,
      "numberOfLetters": 19
    },
    {
      "answer": "Alls Well That Ends Well",
      "numberOfWords": 5,
      "numberOfLetters": 20
    },
    {
      "answer": "Amazing Spring Day",
      "numberOfWords": 3,
      "numberOfLetters": 16
    },
    {
      "answer": "American Traditions",
      "numberOfWords": 2,
      "numberOfLetters": 18
    },
    {
      "answer": "Americas Got Talent",
      "numberOfWords": 3,
      "numberOfLetters": 17
    },
    {
      "answer": "Americas Next Top Model",
      "numberOfWords": 4,
      "numberOfLetters": 20
    },
    {
      "answer": "Angel Of The Citadel",
      "numberOfWords": 4,
      "numberOfLetters": 17
    },
    {
      "answer": "Angry Birds Knock On Wood Game",
      "numberOfWords": 6,
      "numberOfLetters": 25
    },
    {
      "answer": "Animal Farm",
      "numberOfWords": 2,
      "numberOfLetters": 10
    },
    {
      "answer": "Anne Of Green Gables",
      "numberOfWords": 4,
      "numberOfLetters": 17
    },
    {
      "answer": "Appian Way",
      "numberOfWords": 2,
      "numberOfLetters": 9
    },
    {
      "answer": "Apples To Apples",
      "numberOfWords": 3,
      "numberOfLetters": 14
    },
    {
      "answer": "Articles Of Association",
      "numberOfWords": 3,
      "numberOfLetters": 21
    },
    {
      "answer": "Articles Of Confederation",
      "numberOfWords": 3,
      "numberOfLetters": 23
    },
    {
      "answer": "As You Like It",
      "numberOfWords": 4,
      "numberOfLetters": 11
    },
    {
      "answer": "Avenue Q",
      "numberOfWords": 2,
      "numberOfLetters": 7
    },
    {
      "answer": "Baltimore Blues",
      "numberOfWords": 2,
      "numberOfLetters": 14
    },
    {
      "answer": "Banquet Table",
      "numberOfWords": 2,
      "numberOfLetters": 12
    },
    {
      "answer": "Barefoot In The Park",
      "numberOfWords": 4,
      "numberOfLetters": 17
    },
    {
      "answer": "Bartletts Familiar Quotations",
      "numberOfWords": 3,
      "numberOfLetters": 27
    },
    {
      "answer": "Bass Fiddle",
      "numberOfWords": 2,
      "numberOfLetters": 10
    },
    {
      "answer": "Bass Violin",
      "numberOfWords": 2,
      "numberOfLetters": 10
    },
    {
      "answer": "Battle Of The Sexes",
      "numberOfWords": 4,
      "numberOfLetters": 16
    },
    {
      "answer": "Bay Of Sighs",
      "numberOfWords": 3,
      "numberOfLetters": 10
    },
    {
      "answer": "Beach Blanket Babylon",
      "numberOfWords": 3,
      "numberOfLetters": 19
    },
    {
      "answer": "Beasts Of No Nation",
      "numberOfWords": 4,
      "numberOfLetters": 16
    },
    {
      "answer": "Beautiful The Carole King Musical",
      "numberOfWords": 5,
      "numberOfLetters": 29
    },
    {
      "answer": "Beauty  The Beast",
      "numberOfWords": 3,
      "numberOfLetters": 14
    },
    {
      "answer": "Beauty And The Beast",
      "numberOfWords": 4,
      "numberOfLetters": 17
    },
    {
      "answer": "Beezus And Ramona",
      "numberOfWords": 3,
      "numberOfLetters": 15
    },
    {
      "answer": "Bells Are Ringing",
      "numberOfWords": 3,
      "numberOfLetters": 15
    },
    {
      "answer": "Benchmark",
      "numberOfWords": 1,
      "numberOfLetters": 9
    },
    {
      "answer": "Best Actor In A Leading Role",
      "numberOfWords": 6,
      "numberOfLetters": 23
    },
    {
      "answer": "Best Actor In A Supporting Role",
      "numberOfWords": 6,
      "numberOfLetters": 26
    },
    {
      "answer": "Best Actress In A Leading Role",
      "numberOfWords": 6,
      "numberOfLetters": 25
    },
    {
      "answer": "Best Adapted Screenplay",
      "numberOfWords": 3,
      "numberOfLetters": 21
    },
    {
      "answer": "Best Animated Feature",
      "numberOfWords": 3,
      "numberOfLetters": 19
    },
    {
      "answer": "Best Animated Short Film",
      "numberOfWords": 4,
      "numberOfLetters": 21
    },
    {
      "answer": "Best Behaviour",
      "numberOfWords": 2,
      "numberOfLetters": 13
    },
    {
      "answer": "Best Costume Design",
      "numberOfWords": 3,
      "numberOfLetters": 17
    },
    {
      "answer": "Best Director",
      "numberOfWords": 2,
      "numberOfLetters": 12
    },
    {
      "answer": "Best Dressed Man",
      "numberOfWords": 3,
      "numberOfLetters": 14
    },
    {
      "answer": "Best Original Screenplay",
      "numberOfWords": 3,
      "numberOfLetters": 22
    },
    {
      "answer": "Best Original Song",
      "numberOfWords": 3,
      "numberOfLetters": 16
    },
    {
      "answer": "BestDressed Man",
      "numberOfWords": 2,
      "numberOfLetters": 14
    },
    {
      "answer": "Betrayal At House On The Hill",
      "numberOfWords": 6,
      "numberOfLetters": 24
    },
    {
      "answer": "Better Homes And Gardens",
      "numberOfWords": 4,
      "numberOfLetters": 21
    },
    {
      "answer": "Between The World And Me",
      "numberOfWords": 5,
      "numberOfLetters": 20
    },
    {
      "answer": "Big Waves",
      "numberOfWords": 2,
      "numberOfLetters": 8
    },
    {
      "answer": "Bill Of Rights",
      "numberOfWords": 3,
      "numberOfLetters": 12
    },
    {
      "answer": "Birthstone Ring",
      "numberOfWords": 2,
      "numberOfLetters": 14
    },
    {
      "answer": "Blue Bloods",
      "numberOfWords": 2,
      "numberOfLetters": 10
    },
    {
      "answer": "Blue Highways",
      "numberOfWords": 2,
      "numberOfLetters": 12
    },
    {
      "answer": "Blue Streak",
      "numberOfWords": 2,
      "numberOfLetters": 10
    },
    {
      "answer": "Blue Velvet",
      "numberOfWords": 2,
      "numberOfLetters": 10
    },
    {
      "answer": "Boston Herald",
      "numberOfWords": 2,
      "numberOfLetters": 12
    },
    {
      "answer": "Brave New World",
      "numberOfWords": 3,
      "numberOfLetters": 13
    },
    {
      "answer": "Bread And Jam For Francis",
      "numberOfWords": 5,
      "numberOfLetters": 21
    },
    {
      "answer": "Breakfast At Tiffanys",
      "numberOfWords": 3,
      "numberOfLetters": 19
    },
    {
      "answer": "Brideshead Revisited",
      "numberOfWords": 2,
      "numberOfLetters": 19
    },
    {
      "answer": "Bright Yellow Sunshine",
      "numberOfWords": 3,
      "numberOfLetters": 20
    },
    {
      "answer": "Brighty Of The Grand Canyon",
      "numberOfWords": 5,
      "numberOfLetters": 23
    },
    {
      "answer": "Brown Bear Brown Bear What Do You See",
      "numberOfWords": 8,
      "numberOfLetters": 30
    },
    {
      "answer": "Brown V Board Of Education",
      "numberOfWords": 5,
      "numberOfLetters": 22
    },
    {
      "answer": "Budget Travel Magazine",
      "numberOfWords": 3,
      "numberOfLetters": 20
    },
    {
      "answer": "Buffalo Bills Wild West Show",
      "numberOfWords": 5,
      "numberOfLetters": 24
    },
    {
      "answer": "Buffers  Polishers",
      "numberOfWords": 2,
      "numberOfLetters": 16
    },
    {
      "answer": "Buffy The Vampire Slayer",
      "numberOfWords": 4,
      "numberOfLetters": 21
    },
    {
      "answer": "Bush Medicine",
      "numberOfWords": 2,
      "numberOfLetters": 12
    },
    {
      "answer": "Business Partners",
      "numberOfWords": 2,
      "numberOfLetters": 16
    },
    {
      "answer": "Bye Bye Birdie",
      "numberOfWords": 3,
      "numberOfLetters": 12
    },
    {
      "answer": "Caketastrophe",
      "numberOfWords": 1,
      "numberOfLetters": 13
    },
    {
      "answer": "Camelot",
      "numberOfWords": 1,
      "numberOfLetters": 7
    },
    {
      "answer": "Cant Fool Me",
      "numberOfWords": 3,
      "numberOfLetters": 10
    },
    {
      "answer": "Cane River",
      "numberOfWords": 2,
      "numberOfLetters": 9
    },
    {
      "answer": "Card Shuffler",
      "numberOfWords": 2,
      "numberOfLetters": 12
    },
    {
      "answer": "Cardigans  Pullovers",
      "numberOfWords": 2,
      "numberOfLetters": 18
    },
    {
      "answer": "Catch Me If You Can",
      "numberOfWords": 5,
      "numberOfLetters": 15
    },
    {
      "answer": "Catwalk",
      "numberOfWords": 1,
      "numberOfLetters": 7
    },
    {
      "answer": "Cbs News Sunday Morning",
      "numberOfWords": 4,
      "numberOfLetters": 20
    },
    {
      "answer": "Charlottes Web",
      "numberOfWords": 2,
      "numberOfLetters": 13
    },
    {
      "answer": "Cheeky Grin",
      "numberOfWords": 2,
      "numberOfLetters": 10
    },
    {
      "answer": "Chicago Sun Times",
      "numberOfWords": 3,
      "numberOfLetters": 15
    },
    {
      "answer": "Childrens Crafts",
      "numberOfWords": 2,
      "numberOfLetters": 15
    },
    {
      "answer": "Cinderella",
      "numberOfWords": 1,
      "numberOfLetters": 10
    },
    {
      "answer": "Clark The Shark",
      "numberOfWords": 3,
      "numberOfLetters": 13
    },
    {
      "answer": "Clear Description",
      "numberOfWords": 2,
      "numberOfLetters": 16
    },
    {
      "answer": "Code To Zero",
      "numberOfWords": 3,
      "numberOfLetters": 10
    },
    {
      "answer": "Collection Of Myths",
      "numberOfWords": 3,
      "numberOfLetters": 17
    },
    {
      "answer": "Comic Books",
      "numberOfWords": 2,
      "numberOfLetters": 10
    },
    {
      "answer": "Commander In Chief",
      "numberOfWords": 3,
      "numberOfLetters": 16
    },
    {
      "answer": "Consumer Reports",
      "numberOfWords": 2,
      "numberOfLetters": 15
    },
    {
      "answer": "Cooks Illustrated",
      "numberOfWords": 2,
      "numberOfLetters": 16
    },
    {
      "answer": "Cosmopolitan",
      "numberOfWords": 1,
      "numberOfLetters": 12
    },
    {
      "answer": "Cracked Sidewalk",
      "numberOfWords": 2,
      "numberOfLetters": 15
    },
    {
      "answer": "Da Vincis The Last Supper",
      "numberOfWords": 5,
      "numberOfLetters": 21
    },
    {
      "answer": "Damn Yankees",
      "numberOfWords": 2,
      "numberOfLetters": 11
    },
    {
      "answer": "Dancing With The Stars Live",
      "numberOfWords": 5,
      "numberOfLetters": 23
    },
    {
      "answer": "Dark Side Of The Moon",
      "numberOfWords": 5,
      "numberOfLetters": 17
    },
    {
      "answer": "Daughter Of Fortune",
      "numberOfWords": 3,
      "numberOfLetters": 17
    },
    {
      "answer": "Declaration Of Independence",
      "numberOfWords": 3,
      "numberOfLetters": 25
    },
    {
      "answer": "Descent Into Limbo",
      "numberOfWords": 3,
      "numberOfLetters": 16
    },
    {
      "answer": "Dexter",
      "numberOfWords": 1,
      "numberOfLetters": 6
    },
    {
      "answer": "Diddle Diddle Dumpling",
      "numberOfWords": 3,
      "numberOfLetters": 20
    },
    {
      "answer": "Diddle Diddle Dumpling Thing",
      "numberOfWords": 4,
      "numberOfLetters": 25
    },
    {
      "answer": "Do Re Mi",
      "numberOfWords": 3,
      "numberOfLetters": 6
    },
    {
      "answer": "Dont Spill The Beans",
      "numberOfWords": 4,
      "numberOfLetters": 17
    },
    {
      "answer": "Downton Abbey",
      "numberOfWords": 2,
      "numberOfLetters": 12
    },
    {
      "answer": "Downtown Abbey",
      "numberOfWords": 2,
      "numberOfLetters": 13
    },
    {
      "answer": "Dr Seuss Horton Hears A Who",
      "numberOfWords": 6,
      "numberOfLetters": 22
    },
    {
      "answer": "Dragons Love Tacos",
      "numberOfWords": 3,
      "numberOfLetters": 16
    },
    {
      "answer": "Dreamgirls",
      "numberOfWords": 1,
      "numberOfLetters": 10
    },
    {
      "answer": "Eat Pray Love",
      "numberOfWords": 3,
      "numberOfLetters": 11
    },
    {
      "answer": "Elle Magazine",
      "numberOfWords": 2,
      "numberOfLetters": 12
    },
    {
      "answer": "Emancipation Proclamation",
      "numberOfWords": 2,
      "numberOfLetters": 24
    },
    {
      "answer": "Enjoying Some Fun In The Sun",
      "numberOfWords": 6,
      "numberOfLetters": 23
    },
    {
      "answer": "Entertainment Tonight",
      "numberOfWords": 2,
      "numberOfLetters": 20
    },
    {
      "answer": "Entertainment Weekly",
      "numberOfWords": 2,
      "numberOfLetters": 19
    },
    {
      "answer": "Evita",
      "numberOfWords": 1,
      "numberOfLetters": 5
    },
    {
      "answer": "Exciting Thought",
      "numberOfWords": 2,
      "numberOfLetters": 15
    },
    {
      "answer": "Facemask",
      "numberOfWords": 1,
      "numberOfLetters": 8
    },
    {
      "answer": "Family Guy",
      "numberOfWords": 2,
      "numberOfLetters": 9
    },
    {
      "answer": "Fancy Dress Shoes",
      "numberOfWords": 3,
      "numberOfLetters": 15
    },
    {
      "answer": "Fantastic Mr Fox",
      "numberOfWords": 3,
      "numberOfLetters": 14
    },
    {
      "answer": "Fantastic Mr Fox",
      "numberOfWords": 3,
      "numberOfLetters": 14
    },
    {
      "answer": "Farmers Almanac",
      "numberOfWords": 2,
      "numberOfLetters": 14
    },
    {
      "answer": "Fashion Insiders",
      "numberOfWords": 2,
      "numberOfLetters": 15
    },
    {
      "answer": "Fast Company",
      "numberOfWords": 2,
      "numberOfLetters": 11
    },
    {
      "answer": "Fast Food Nation",
      "numberOfWords": 3,
      "numberOfLetters": 14
    },
    {
      "answer": "Fat Albert And The Cosby Kids",
      "numberOfWords": 6,
      "numberOfLetters": 24
    },
    {
      "answer": "Fearless Fourteen",
      "numberOfWords": 2,
      "numberOfLetters": 16
    },
    {
      "answer": "Female Vocalist Of The Year",
      "numberOfWords": 5,
      "numberOfLetters": 23
    },
    {
      "answer": "Fiddler On The Roof",
      "numberOfWords": 4,
      "numberOfLetters": 16
    },
    {
      "answer": "Film Studies",
      "numberOfWords": 2,
      "numberOfLetters": 11
    },
    {
      "answer": "Finding Neverland",
      "numberOfWords": 2,
      "numberOfLetters": 16
    },
    {
      "answer": "Firemans Axe",
      "numberOfWords": 2,
      "numberOfLetters": 11
    },
    {
      "answer": "First Choice",
      "numberOfWords": 2,
      "numberOfLetters": 11
    },
    {
      "answer": "FloorToCeiling Views",
      "numberOfWords": 2,
      "numberOfLetters": 19
    },
    {
      "answer": "Flower Drum Song",
      "numberOfWords": 3,
      "numberOfLetters": 14
    },
    {
      "answer": "Flying Magazine",
      "numberOfWords": 2,
      "numberOfLetters": 14
    },
    {
      "answer": "Follow The River",
      "numberOfWords": 3,
      "numberOfLetters": 14
    },
    {
      "answer": "For Whom The Bell Tolls",
      "numberOfWords": 5,
      "numberOfLetters": 19
    },
    {
      "answer": "Forbidden Desert",
      "numberOfWords": 2,
      "numberOfLetters": 15
    },
    {
      "answer": "Forbidden Island",
      "numberOfWords": 2,
      "numberOfLetters": 15
    },
    {
      "answer": "Foundation",
      "numberOfWords": 1,
      "numberOfLetters": 10
    },
    {
      "answer": "Foxs Prison Break",
      "numberOfWords": 3,
      "numberOfLetters": 15
    },
    {
      "answer": "Freaky Friday",
      "numberOfWords": 2,
      "numberOfLetters": 12
    },
    {
      "answer": "Freebie And The Bean",
      "numberOfWords": 4,
      "numberOfLetters": 17
    },
    {
      "answer": "French Lessons",
      "numberOfWords": 2,
      "numberOfLetters": 13
    },
    {
      "answer": "Frog And Toad Are Friends",
      "numberOfWords": 5,
      "numberOfLetters": 21
    },
    {
      "answer": "From Here To Eternity",
      "numberOfWords": 4,
      "numberOfLetters": 18
    },
    {
      "answer": "Frontline",
      "numberOfWords": 1,
      "numberOfLetters": 9
    },
    {
      "answer": "Fun Home",
      "numberOfWords": 2,
      "numberOfLetters": 7
    },
    {
      "answer": "Funny Situation",
      "numberOfWords": 2,
      "numberOfLetters": 14
    },
    {
      "answer": "Funny Stories",
      "numberOfWords": 2,
      "numberOfLetters": 12
    },
    {
      "answer": "Futurama",
      "numberOfWords": 1,
      "numberOfLetters": 8
    },
    {
      "answer": "G Is For Gumshoe",
      "numberOfWords": 4,
      "numberOfLetters": 13
    },
    {
      "answer": "Gallery Of The Louvre",
      "numberOfWords": 4,
      "numberOfLetters": 18
    },
    {
      "answer": "Game Informer",
      "numberOfWords": 2,
      "numberOfLetters": 12
    },
    {
      "answer": "Game Of Thrones",
      "numberOfWords": 3,
      "numberOfLetters": 13
    },
    {
      "answer": "Garden Of Shadows",
      "numberOfWords": 3,
      "numberOfLetters": 15
    },
    {
      "answer": "Gates Of Fire",
      "numberOfWords": 3,
      "numberOfLetters": 11
    },
    {
      "answer": "Gator Boys",
      "numberOfWords": 2,
      "numberOfLetters": 9
    },
    {
      "answer": "General Theory Of Relativity",
      "numberOfWords": 4,
      "numberOfLetters": 25
    },
    {
      "answer": "Gentlemans Quarterly",
      "numberOfWords": 2,
      "numberOfLetters": 19
    },
    {
      "answer": "Gettysburg Address",
      "numberOfWords": 2,
      "numberOfLetters": 17
    },
    {
      "answer": "Girl In A Band A Memoir",
      "numberOfWords": 6,
      "numberOfLetters": 18
    },
    {
      "answer": "Girl In Red Dress With Cat And Dog",
      "numberOfWords": 8,
      "numberOfLetters": 27
    },
    {
      "answer": "Globe Magazine",
      "numberOfWords": 2,
      "numberOfLetters": 13
    },
    {
      "answer": "Globe Of The World",
      "numberOfWords": 4,
      "numberOfLetters": 15
    },
    {
      "answer": "Go Set A Watchman",
      "numberOfWords": 4,
      "numberOfLetters": 14
    },
    {
      "answer": "Goldilocks  The Three Bears",
      "numberOfWords": 4,
      "numberOfLetters": 23
    },
    {
      "answer": "Gone With The Wind",
      "numberOfWords": 4,
      "numberOfLetters": 15
    },
    {
      "answer": "Good Breaks",
      "numberOfWords": 2,
      "numberOfLetters": 10
    },
    {
      "answer": "Good Housekeeping",
      "numberOfWords": 2,
      "numberOfLetters": 16
    },
    {
      "answer": "Goodnight Moon",
      "numberOfWords": 2,
      "numberOfLetters": 13
    },
    {
      "answer": "Gossip Girl",
      "numberOfWords": 2,
      "numberOfLetters": 10
    },
    {
      "answer": "Grease",
      "numberOfWords": 1,
      "numberOfLetters": 6
    },
    {
      "answer": "Great Big Hug",
      "numberOfWords": 3,
      "numberOfLetters": 11
    },
    {
      "answer": "Green Eggs And Ham",
      "numberOfWords": 4,
      "numberOfLetters": 15
    },
    {
      "answer": "Grimms Fairy Tales",
      "numberOfWords": 3,
      "numberOfLetters": 16
    },
    {
      "answer": "Groovy Time",
      "numberOfWords": 2,
      "numberOfLetters": 10
    },
    {
      "answer": "Guinness Book Of World Records",
      "numberOfWords": 5,
      "numberOfLetters": 26
    },
    {
      "answer": "Gullivers Travels",
      "numberOfWords": 2,
      "numberOfLetters": 16
    },
    {
      "answer": "Guys And Dolls",
      "numberOfWords": 3,
      "numberOfLetters": 12
    },
    {
      "answer": "Hairbrained Scheme",
      "numberOfWords": 2,
      "numberOfLetters": 17
    },
    {
      "answer": "Hairspray",
      "numberOfWords": 1,
      "numberOfLetters": 9
    },
    {
      "answer": "Half Of A Yellow Sun",
      "numberOfWords": 5,
      "numberOfLetters": 16
    },
    {
      "answer": "Hannah And Her Sisters",
      "numberOfWords": 4,
      "numberOfLetters": 19
    },
    {
      "answer": "Happy Feet",
      "numberOfWords": 2,
      "numberOfLetters": 9
    },
    {
      "answer": "Hard Knocks",
      "numberOfWords": 2,
      "numberOfLetters": 10
    },
    {
      "answer": "Harold And The Purple Crayon",
      "numberOfWords": 5,
      "numberOfLetters": 24
    },
    {
      "answer": "Harpers Magazine",
      "numberOfWords": 2,
      "numberOfLetters": 15
    },
    {
      "answer": "Harry Potter And The Chamber Of Secrets",
      "numberOfWords": 7,
      "numberOfLetters": 33
    },
    {
      "answer": "Harry Potter And The Goblet Of Fire",
      "numberOfWords": 7,
      "numberOfLetters": 29
    },
    {
      "answer": "Harry Potter And The Prisoner Of Azkaban",
      "numberOfWords": 7,
      "numberOfLetters": 34
    },
    {
      "answer": "Harry Potter And The Sorcerers Stone",
      "numberOfWords": 6,
      "numberOfLetters": 31
    },
    {
      "answer": "Harry Potter Coloring Book",
      "numberOfWords": 4,
      "numberOfLetters": 23
    },
    {
      "answer": "Harry Potter Colouring Book",
      "numberOfWords": 4,
      "numberOfLetters": 24
    },
    {
      "answer": "Hbos Inside The Nfl",
      "numberOfWords": 4,
      "numberOfLetters": 16
    },
    {
      "answer": "He Shed She Shed",
      "numberOfWords": 4,
      "numberOfLetters": 13
    },
    {
      "answer": "Health And Human Right Journal",
      "numberOfWords": 5,
      "numberOfLetters": 26
    },
    {
      "answer": "Health And Human Rights Journal",
      "numberOfWords": 5,
      "numberOfLetters": 27
    },
    {
      "answer": "Heart Of Darkness",
      "numberOfWords": 3,
      "numberOfLetters": 15
    },
    {
      "answer": "Heartfelt Thanks",
      "numberOfWords": 2,
      "numberOfLetters": 15
    },
    {
      "answer": "Hedwig And The Angry Inch",
      "numberOfWords": 5,
      "numberOfLetters": 21
    },
    {
      "answer": "Here On Earth",
      "numberOfWords": 3,
      "numberOfLetters": 11
    },
    {
      "answer": "Hgtv Magazine",
      "numberOfWords": 2,
      "numberOfLetters": 12
    },
    {
      "answer": "High Fashion",
      "numberOfWords": 2,
      "numberOfLetters": 11
    },
    {
      "answer": "High School Musical",
      "numberOfWords": 3,
      "numberOfLetters": 17
    },
    {
      "answer": "Hill Street Blues",
      "numberOfWords": 3,
      "numberOfLetters": 15
    },
    {
      "answer": "Home Project",
      "numberOfWords": 2,
      "numberOfLetters": 11
    },
    {
      "answer": "Homers The Iliad",
      "numberOfWords": 3,
      "numberOfLetters": 14
    },
    {
      "answer": "Honky Tonk Samurai",
      "numberOfWords": 3,
      "numberOfLetters": 16
    },
    {
      "answer": "Hot Cross Buns",
      "numberOfWords": 3,
      "numberOfLetters": 12
    },
    {
      "answer": "Hotels Of North America",
      "numberOfWords": 4,
      "numberOfLetters": 20
    },
    {
      "answer": "House Of Leaves",
      "numberOfWords": 3,
      "numberOfLetters": 13
    },
    {
      "answer": "House On Haunted Hill",
      "numberOfWords": 4,
      "numberOfLetters": 18
    },
    {
      "answer": "How To Train Your Dragon",
      "numberOfWords": 5,
      "numberOfLetters": 20
    },
    {
      "answer": "Humanitarian Award",
      "numberOfWords": 2,
      "numberOfLetters": 17
    },
    {
      "answer": "Hush Little Baby",
      "numberOfWords": 3,
      "numberOfLetters": 14
    },
    {
      "answer": "I Am Number Four",
      "numberOfWords": 4,
      "numberOfLetters": 13
    },
    {
      "answer": "If I Ran The Circus",
      "numberOfWords": 5,
      "numberOfLetters": 15
    },
    {
      "answer": "If There Be Thorns",
      "numberOfWords": 4,
      "numberOfLetters": 15
    },
    {
      "answer": "If Youre Not Yet Like Me",
      "numberOfWords": 6,
      "numberOfLetters": 19
    },
    {
      "answer": "In The Country Of Men",
      "numberOfWords": 5,
      "numberOfLetters": 17
    },
    {
      "answer": "Inside Edition",
      "numberOfWords": 2,
      "numberOfLetters": 13
    },
    {
      "answer": "Its The Great Pumpkin Charlie Brown",
      "numberOfWords": 6,
      "numberOfLetters": 30
    },
    {
      "answer": "Jabberwocky",
      "numberOfWords": 1,
      "numberOfLetters": 11
    },
    {
      "answer": "Jack And The Beanstalk",
      "numberOfWords": 4,
      "numberOfLetters": 19
    },
    {
      "answer": "James And The Giant Peach",
      "numberOfWords": 5,
      "numberOfLetters": 21
    },
    {
      "answer": "Jason And The Golden Fleece",
      "numberOfWords": 5,
      "numberOfLetters": 23
    },
    {
      "answer": "Jersey Boys",
      "numberOfWords": 2,
      "numberOfLetters": 10
    },
    {
      "answer": "Jersey Boys The Musical",
      "numberOfWords": 4,
      "numberOfLetters": 20
    },
    {
      "answer": "Johnny Tremain",
      "numberOfWords": 2,
      "numberOfLetters": 13
    },
    {
      "answer": "Josie And The Pussycats",
      "numberOfWords": 4,
      "numberOfLetters": 20
    },
    {
      "answer": "June Moon",
      "numberOfWords": 2,
      "numberOfLetters": 8
    },
    {
      "answer": "Kaleidoscope Hearts",
      "numberOfWords": 2,
      "numberOfLetters": 18
    },
    {
      "answer": "Kelley Blue Book",
      "numberOfWords": 3,
      "numberOfLetters": 14
    },
    {
      "answer": "Key Play Of The Game",
      "numberOfWords": 5,
      "numberOfLetters": 16
    },
    {
      "answer": "King Of The Hill",
      "numberOfWords": 4,
      "numberOfLetters": 13
    },
    {
      "answer": "Kinky Boots",
      "numberOfWords": 2,
      "numberOfLetters": 10
    },
    {
      "answer": "Kiss Me Kate",
      "numberOfWords": 3,
      "numberOfLetters": 10
    },
    {
      "answer": "Kitchen Confidential",
      "numberOfWords": 2,
      "numberOfLetters": 19
    },
    {
      "answer": "KneeJerk Reaction",
      "numberOfWords": 2,
      "numberOfLetters": 16
    },
    {
      "answer": "La Cage Aux Folles",
      "numberOfWords": 4,
      "numberOfLetters": 15
    },
    {
      "answer": "La Confidential",
      "numberOfWords": 2,
      "numberOfLetters": 14
    },
    {
      "answer": "Ladies Home Journal",
      "numberOfWords": 3,
      "numberOfLetters": 17
    },
    {
      "answer": "Lara Croft Tomb Raider",
      "numberOfWords": 4,
      "numberOfLetters": 19
    },
    {
      "answer": "Las Vegas ReviewJournal",
      "numberOfWords": 3,
      "numberOfLetters": 21
    },
    {
      "answer": "LaughOut Loud Jokes For Kids",
      "numberOfWords": 5,
      "numberOfLetters": 24
    },
    {
      "answer": "LaughOutLoud Jokes For Kids",
      "numberOfWords": 4,
      "numberOfLetters": 24
    },
    {
      "answer": "Lead Weight",
      "numberOfWords": 2,
      "numberOfLetters": 10
    },
    {
      "answer": "Lean Mean Thirteen",
      "numberOfWords": 3,
      "numberOfLetters": 16
    },
    {
      "answer": "Legally Blonde The Musical",
      "numberOfWords": 4,
      "numberOfLetters": 23
    },
    {
      "answer": "Lend Me A Tenor",
      "numberOfWords": 4,
      "numberOfLetters": 12
    },
    {
      "answer": "Les Miserables",
      "numberOfWords": 2,
      "numberOfLetters": 13
    },
    {
      "answer": "Less Than Zero",
      "numberOfWords": 3,
      "numberOfLetters": 12
    },
    {
      "answer": "Lets Go Fishin Game",
      "numberOfWords": 4,
      "numberOfLetters": 16
    },
    {
      "answer": "Lets Walk To The Middle Of The Ocean",
      "numberOfWords": 8,
      "numberOfLetters": 29
    },
    {
      "answer": "Lie To Me",
      "numberOfWords": 3,
      "numberOfLetters": 7
    },
    {
      "answer": "Like Water For Chocolate",
      "numberOfWords": 4,
      "numberOfLetters": 21
    },
    {
      "answer": "Lilys Purple Plastic Purse",
      "numberOfWords": 4,
      "numberOfLetters": 23
    },
    {
      "answer": "Little Bear",
      "numberOfWords": 2,
      "numberOfLetters": 10
    },
    {
      "answer": "Little Blue Trucks Halloween",
      "numberOfWords": 4,
      "numberOfLetters": 25
    },
    {
      "answer": "Little Red Hen",
      "numberOfWords": 3,
      "numberOfLetters": 12
    },
    {
      "answer": "Little Women",
      "numberOfWords": 2,
      "numberOfLetters": 11
    },
    {
      "answer": "Living In The USA",
      "numberOfWords": 4,
      "numberOfLetters": 14
    },
    {
      "answer": "Lonesome Dove",
      "numberOfWords": 2,
      "numberOfLetters": 12
    },
    {
      "answer": "Looney Tunes",
      "numberOfWords": 2,
      "numberOfLetters": 11
    },
    {
      "answer": "Los Angeles Times",
      "numberOfWords": 3,
      "numberOfLetters": 15
    },
    {
      "answer": "Lost In Yonkers",
      "numberOfWords": 3,
      "numberOfLetters": 13
    },
    {
      "answer": "Love In A Fallen City",
      "numberOfWords": 5,
      "numberOfLetters": 17
    },
    {
      "answer": "LowEmission Vehicle",
      "numberOfWords": 2,
      "numberOfLetters": 18
    },
    {
      "answer": "Lucky Peer",
      "numberOfWords": 2,
      "numberOfLetters": 9
    },
    {
      "answer": "Lunch Menu",
      "numberOfWords": 2,
      "numberOfLetters": 9
    },
    {
      "answer": "Macbeth",
      "numberOfWords": 1,
      "numberOfLetters": 7
    },
    {
      "answer": "Madame X",
      "numberOfWords": 2,
      "numberOfLetters": 7
    },
    {
      "answer": "Magificent Views",
      "numberOfWords": 2,
      "numberOfLetters": 15
    },
    {
      "answer": "Make Way For Ducklings",
      "numberOfWords": 4,
      "numberOfLetters": 19
    },
    {
      "answer": "Male Vocalist Of The Year",
      "numberOfWords": 5,
      "numberOfLetters": 21
    },
    {
      "answer": "Mamma Mia",
      "numberOfWords": 2,
      "numberOfLetters": 8
    },
    {
      "answer": "Man Of La Mancha",
      "numberOfWords": 4,
      "numberOfLetters": 13
    },
    {
      "answer": "Manifest Destiny",
      "numberOfWords": 2,
      "numberOfLetters": 15
    },
    {
      "answer": "Marie Claire",
      "numberOfWords": 2,
      "numberOfLetters": 11
    },
    {
      "answer": "Martha Stewart Living",
      "numberOfWords": 3,
      "numberOfLetters": 19
    },
    {
      "answer": "Marvel Universe Live",
      "numberOfWords": 3,
      "numberOfLetters": 18
    },
    {
      "answer": "Masterpiece Theatre",
      "numberOfWords": 2,
      "numberOfLetters": 18
    },
    {
      "answer": "Matilda",
      "numberOfWords": 1,
      "numberOfLetters": 7
    },
    {
      "answer": "Mechanical Bull",
      "numberOfWords": 2,
      "numberOfLetters": 14
    },
    {
      "answer": "Memoirs Of A Geisha",
      "numberOfWords": 4,
      "numberOfLetters": 16
    },
    {
      "answer": "Mens Health",
      "numberOfWords": 2,
      "numberOfLetters": 10
    },
    {
      "answer": "Merchant Of Venice",
      "numberOfWords": 3,
      "numberOfLetters": 16
    },
    {
      "answer": "Message In A Bottle",
      "numberOfWords": 4,
      "numberOfLetters": 16
    },
    {
      "answer": "Mighty Morphin Power Rangers",
      "numberOfWords": 4,
      "numberOfLetters": 25
    },
    {
      "answer": "Mike  Mike",
      "numberOfWords": 2,
      "numberOfLetters": 8
    },
    {
      "answer": "Miss Saigon",
      "numberOfWords": 2,
      "numberOfLetters": 10
    },
    {
      "answer": "Molecular Biology",
      "numberOfWords": 2,
      "numberOfLetters": 16
    },
    {
      "answer": "Mondays Child",
      "numberOfWords": 2,
      "numberOfLetters": 12
    },
    {
      "answer": "Monopoly Junior",
      "numberOfWords": 2,
      "numberOfLetters": 14
    },
    {
      "answer": "Mother Of Pearl",
      "numberOfWords": 3,
      "numberOfLetters": 13
    },
    {
      "answer": "Mouse Trap",
      "numberOfWords": 2,
      "numberOfLetters": 9
    },
    {
      "answer": "Mr Mustache Goes To The Circus",
      "numberOfWords": 6,
      "numberOfLetters": 25
    },
    {
      "answer": "Mr Poppers Penguins",
      "numberOfWords": 3,
      "numberOfLetters": 17
    },
    {
      "answer": "Much Ado About Nothing",
      "numberOfWords": 4,
      "numberOfLetters": 19
    },
    {
      "answer": "Muscle  Fitness",
      "numberOfWords": 2,
      "numberOfLetters": 13
    },
    {
      "answer": "My Last Duchess",
      "numberOfWords": 3,
      "numberOfLetters": 13
    },
    {
      "answer": "My Life On The Road",
      "numberOfWords": 5,
      "numberOfLetters": 15
    },
    {
      "answer": "My Side Of The Mountain",
      "numberOfWords": 5,
      "numberOfLetters": 19
    },
    {
      "answer": "My Traitors Heart",
      "numberOfWords": 3,
      "numberOfLetters": 15
    },
    {
      "answer": "Nation Enquirer",
      "numberOfWords": 2,
      "numberOfLetters": 14
    },
    {
      "answer": "National Enquire",
      "numberOfWords": 2,
      "numberOfLetters": 15
    },
    {
      "answer": "National Enquirer",
      "numberOfWords": 2,
      "numberOfLetters": 16
    },
    {
      "answer": "National Geographic",
      "numberOfWords": 2,
      "numberOfLetters": 18
    },
    {
      "answer": "National Geographic Kids",
      "numberOfWords": 3,
      "numberOfLetters": 22
    },
    {
      "answer": "National Geographic Magazine",
      "numberOfWords": 3,
      "numberOfLetters": 26
    },
    {
      "answer": "Natural Histories",
      "numberOfWords": 2,
      "numberOfLetters": 16
    },
    {
      "answer": "Naturaleigh Phenomenon",
      "numberOfWords": 2,
      "numberOfLetters": 21
    },
    {
      "answer": "New Artist Of The Year",
      "numberOfWords": 5,
      "numberOfLetters": 18
    },
    {
      "answer": "New York Magazine",
      "numberOfWords": 3,
      "numberOfLetters": 15
    },
    {
      "answer": "Nineteenth Amendment",
      "numberOfWords": 2,
      "numberOfLetters": 19
    },
    {
      "answer": "No Man Is An Island",
      "numberOfWords": 5,
      "numberOfLetters": 15
    },
    {
      "answer": "No Stress Chess",
      "numberOfWords": 3,
      "numberOfLetters": 13
    },
    {
      "answer": "Notes From A Small Island",
      "numberOfWords": 5,
      "numberOfLetters": 21
    },
    {
      "answer": "Notorious Nineteen",
      "numberOfWords": 2,
      "numberOfLetters": 17
    },
    {
      "answer": "Odd Hours",
      "numberOfWords": 2,
      "numberOfLetters": 8
    },
    {
      "answer": "Odds And Ends",
      "numberOfWords": 3,
      "numberOfLetters": 11
    },
    {
      "answer": "Of Mice And Men",
      "numberOfWords": 4,
      "numberOfLetters": 12
    },
    {
      "answer": "Oh The Places Youll Go",
      "numberOfWords": 5,
      "numberOfLetters": 18
    },
    {
      "answer": "Oklahoma",
      "numberOfWords": 1,
      "numberOfLetters": 8
    },
    {
      "answer": "Oklahoma",
      "numberOfWords": 1,
      "numberOfLetters": 8
    },
    {
      "answer": "Old Macdonald Had A Farm",
      "numberOfWords": 5,
      "numberOfLetters": 20
    },
    {
      "answer": "On Her Majestys Secret Service",
      "numberOfWords": 5,
      "numberOfLetters": 26
    },
    {
      "answer": "On The Road",
      "numberOfWords": 3,
      "numberOfLetters": 9
    },
    {
      "answer": "On The Town",
      "numberOfWords": 3,
      "numberOfLetters": 9
    },
    {
      "answer": "On Your Feet",
      "numberOfWords": 3,
      "numberOfLetters": 10
    },
    {
      "answer": "Once Upon A Mattress",
      "numberOfWords": 4,
      "numberOfLetters": 17
    },
    {
      "answer": "One Thousand And One Nights",
      "numberOfWords": 5,
      "numberOfLetters": 23
    },
    {
      "answer": "Opportunity Of A Lifetime",
      "numberOfWords": 4,
      "numberOfLetters": 22
    },
    {
      "answer": "Original Historical Documents",
      "numberOfWords": 3,
      "numberOfLetters": 27
    },
    {
      "answer": "Othello",
      "numberOfWords": 1,
      "numberOfLetters": 7
    },
    {
      "answer": "Outlander",
      "numberOfWords": 1,
      "numberOfLetters": 9
    },
    {
      "answer": "Outstanding Vocal Performance",
      "numberOfWords": 3,
      "numberOfLetters": 27
    },
    {
      "answer": "Oxford Companion To Food",
      "numberOfWords": 4,
      "numberOfLetters": 21
    },
    {
      "answer": "Pandemic On The Brink Expansion",
      "numberOfWords": 5,
      "numberOfLetters": 27
    },
    {
      "answer": "Pandemic On The Brink Of Expansion",
      "numberOfWords": 6,
      "numberOfLetters": 29
    },
    {
      "answer": "Paramour",
      "numberOfWords": 1,
      "numberOfLetters": 8
    },
    {
      "answer": "Patron Saints Of Venice",
      "numberOfWords": 4,
      "numberOfLetters": 20
    },
    {
      "answer": "Paul Reveres Ride",
      "numberOfWords": 3,
      "numberOfLetters": 15
    },
    {
      "answer": "Pease Porridge Hot",
      "numberOfWords": 3,
      "numberOfLetters": 16
    },
    {
      "answer": "People Magazine",
      "numberOfWords": 2,
      "numberOfLetters": 14
    },
    {
      "answer": "Percy Jackson Sea Of Monsters",
      "numberOfWords": 5,
      "numberOfLetters": 25
    },
    {
      "answer": "Perfection",
      "numberOfWords": 1,
      "numberOfLetters": 10
    },
    {
      "answer": "Petals On The Wind",
      "numberOfWords": 4,
      "numberOfLetters": 15
    },
    {
      "answer": "Philadelphia Inquirer",
      "numberOfWords": 2,
      "numberOfLetters": 20
    },
    {
      "answer": "Physical Education",
      "numberOfWords": 2,
      "numberOfLetters": 17
    },
    {
      "answer": "Piano Sanato",
      "numberOfWords": 2,
      "numberOfLetters": 11
    },
    {
      "answer": "Picture Postcard",
      "numberOfWords": 2,
      "numberOfLetters": 15
    },
    {
      "answer": "Play Station How The Grich Stole Xmas",
      "numberOfWords": 7,
      "numberOfLetters": 31
    },
    {
      "answer": "Plush Soft Bathrobe",
      "numberOfWords": 3,
      "numberOfLetters": 17
    },
    {
      "answer": "PointyToe Heels",
      "numberOfWords": 2,
      "numberOfLetters": 14
    },
    {
      "answer": "Political Campaign",
      "numberOfWords": 2,
      "numberOfLetters": 17
    },
    {
      "answer": "Popular Science",
      "numberOfWords": 2,
      "numberOfLetters": 14
    },
    {
      "answer": "Porches  Decks",
      "numberOfWords": 2,
      "numberOfLetters": 12
    },
    {
      "answer": "Portrait Of The Artists Mother",
      "numberOfWords": 5,
      "numberOfLetters": 26
    },
    {
      "answer": "Positive Feedback",
      "numberOfWords": 2,
      "numberOfLetters": 16
    },
    {
      "answer": "Prepackaged Parachute",
      "numberOfWords": 2,
      "numberOfLetters": 20
    },
    {
      "answer": "President Elect",
      "numberOfWords": 2,
      "numberOfLetters": 14
    },
    {
      "answer": "Pride And Prejudice",
      "numberOfWords": 3,
      "numberOfLetters": 17
    },
    {
      "answer": "Private Lives",
      "numberOfWords": 2,
      "numberOfLetters": 12
    },
    {
      "answer": "Prodigal Summer",
      "numberOfWords": 2,
      "numberOfLetters": 14
    },
    {
      "answer": "Prolific Actor",
      "numberOfWords": 2,
      "numberOfLetters": 13
    },
    {
      "answer": "Pulitzer Prize",
      "numberOfWords": 2,
      "numberOfLetters": 13
    },
    {
      "answer": "Puss In Boots",
      "numberOfWords": 3,
      "numberOfLetters": 11
    },
    {
      "answer": "Q Is For Quarry",
      "numberOfWords": 4,
      "numberOfLetters": 12
    },
    {
      "answer": "Quran",
      "numberOfWords": 1,
      "numberOfLetters": 5
    },
    {
      "answer": "R Is For Ricochet",
      "numberOfWords": 4,
      "numberOfLetters": 14
    },
    {
      "answer": "RL Stines The Haunting Hour",
      "numberOfWords": 5,
      "numberOfLetters": 23
    },
    {
      "answer": "Rabbit Hole",
      "numberOfWords": 2,
      "numberOfLetters": 10
    },
    {
      "answer": "Ravensburger Labyrinth",
      "numberOfWords": 2,
      "numberOfLetters": 21
    },
    {
      "answer": "Readers Digest",
      "numberOfWords": 2,
      "numberOfLetters": 13
    },
    {
      "answer": "Reverse Charades",
      "numberOfWords": 2,
      "numberOfLetters": 15
    },
    {
      "answer": "Richard Scarrys Busytown Eye Found It",
      "numberOfWords": 6,
      "numberOfLetters": 32
    },
    {
      "answer": "Richard Scarrys Eye Found It",
      "numberOfWords": 5,
      "numberOfLetters": 24
    },
    {
      "answer": "Ring Around The Rosie",
      "numberOfWords": 4,
      "numberOfLetters": 18
    },
    {
      "answer": "River Cross My Heart",
      "numberOfWords": 4,
      "numberOfLetters": 17
    },
    {
      "answer": "Rogets Thesaurus",
      "numberOfWords": 2,
      "numberOfLetters": 15
    },
    {
      "answer": "Rolling Stone Magazine",
      "numberOfWords": 3,
      "numberOfLetters": 20
    },
    {
      "answer": "Romeo And Juliet",
      "numberOfWords": 3,
      "numberOfLetters": 14
    },
    {
      "answer": "Rugby World Cup",
      "numberOfWords": 3,
      "numberOfLetters": 13
    },
    {
      "answer": "Russell The Sheep",
      "numberOfWords": 3,
      "numberOfLetters": 15
    },
    {
      "answer": "S Is For Silence",
      "numberOfWords": 4,
      "numberOfLetters": 13
    },
    {
      "answer": "Saint Paul The Hermit",
      "numberOfWords": 4,
      "numberOfLetters": 18
    },
    {
      "answer": "Salon Magazine",
      "numberOfWords": 2,
      "numberOfLetters": 13
    },
    {
      "answer": "Salt To The Sea",
      "numberOfWords": 4,
      "numberOfLetters": 12
    },
    {
      "answer": "Samurai Jack",
      "numberOfWords": 2,
      "numberOfLetters": 11
    },
    {
      "answer": "San Francisco Chronicle",
      "numberOfWords": 3,
      "numberOfLetters": 21
    },
    {
      "answer": "Satellite Phone",
      "numberOfWords": 2,
      "numberOfLetters": 14
    },
    {
      "answer": "Say Anything",
      "numberOfWords": 2,
      "numberOfLetters": 11
    },
    {
      "answer": "Schoolhouse Rock",
      "numberOfWords": 2,
      "numberOfLetters": 15
    },
    {
      "answer": "Scientific American",
      "numberOfWords": 2,
      "numberOfLetters": 18
    },
    {
      "answer": "Seeds Of Yeserday",
      "numberOfWords": 3,
      "numberOfLetters": 15
    },
    {
      "answer": "Seeds Of Yesterday",
      "numberOfWords": 3,
      "numberOfLetters": 16
    },
    {
      "answer": "Sense And Sensibility",
      "numberOfWords": 3,
      "numberOfLetters": 19
    },
    {
      "answer": "Sgt Peppers Lonely Hearts Club Band",
      "numberOfWords": 6,
      "numberOfLetters": 30
    },
    {
      "answer": "Shadows Over Camelot",
      "numberOfWords": 3,
      "numberOfLetters": 18
    },
    {
      "answer": "Shark Week",
      "numberOfWords": 2,
      "numberOfLetters": 9
    },
    {
      "answer": "Sheriff Of Nottingham",
      "numberOfWords": 3,
      "numberOfLetters": 19
    },
    {
      "answer": "Shocking Story",
      "numberOfWords": 2,
      "numberOfLetters": 13
    },
    {
      "answer": "Shogun",
      "numberOfWords": 1,
      "numberOfLetters": 6
    },
    {
      "answer": "Shopping Guide",
      "numberOfWords": 2,
      "numberOfLetters": 13
    },
    {
      "answer": "Show Boat",
      "numberOfWords": 2,
      "numberOfLetters": 8
    },
    {
      "answer": "Sideways",
      "numberOfWords": 1,
      "numberOfLetters": 8
    },
    {
      "answer": "Simon And The Witch",
      "numberOfWords": 4,
      "numberOfLetters": 16
    },
    {
      "answer": "Sing A Song Of Sixpence",
      "numberOfWords": 5,
      "numberOfLetters": 19
    },
    {
      "answer": "SketchComic Series",
      "numberOfWords": 2,
      "numberOfLetters": 17
    },
    {
      "answer": "Smokey Joes Cafe",
      "numberOfWords": 3,
      "numberOfLetters": 14
    },
    {
      "answer": "Snow White  The Seven Dwarfs",
      "numberOfWords": 5,
      "numberOfLetters": 23
    },
    {
      "answer": "Snow White And The Seven Dwarfs",
      "numberOfWords": 6,
      "numberOfLetters": 26
    },
    {
      "answer": "Social Studies",
      "numberOfWords": 2,
      "numberOfLetters": 13
    },
    {
      "answer": "Solaris By Stanislaw Lem",
      "numberOfWords": 4,
      "numberOfLetters": 21
    },
    {
      "answer": "Something Rotten",
      "numberOfWords": 2,
      "numberOfLetters": 15
    },
    {
      "answer": "Something Wicked This Way Comes",
      "numberOfWords": 5,
      "numberOfLetters": 27
    },
    {
      "answer": "Song Of Solomon",
      "numberOfWords": 3,
      "numberOfLetters": 13
    },
    {
      "answer": "Sorry",
      "numberOfWords": 1,
      "numberOfLetters": 5
    },
    {
      "answer": "Southern Living",
      "numberOfWords": 2,
      "numberOfLetters": 14
    },
    {
      "answer": "Spectacular Displays Of Christmas Lights",
      "numberOfWords": 5,
      "numberOfLetters": 36
    },
    {
      "answer": "Splat The Cat",
      "numberOfWords": 3,
      "numberOfLetters": 11
    },
    {
      "answer": "Splendor",
      "numberOfWords": 1,
      "numberOfLetters": 8
    },
    {
      "answer": "Sports Illustrated",
      "numberOfWords": 2,
      "numberOfLetters": 17
    },
    {
      "answer": "Spring Awakening",
      "numberOfWords": 2,
      "numberOfLetters": 15
    },
    {
      "answer": "St Joseph In The Forrest",
      "numberOfWords": 5,
      "numberOfLetters": 20
    },
    {
      "answer": "St Louis PostDispatch",
      "numberOfWords": 3,
      "numberOfLetters": 19
    },
    {
      "answer": "Stand By Me",
      "numberOfWords": 3,
      "numberOfLetters": 9
    },
    {
      "answer": "Star Magazine",
      "numberOfWords": 2,
      "numberOfLetters": 12
    },
    {
      "answer": "Station Eleven",
      "numberOfWords": 2,
      "numberOfLetters": 13
    },
    {
      "answer": "StockMarket Quotes",
      "numberOfWords": 2,
      "numberOfLetters": 17
    },
    {
      "answer": "Stone Of Destiny",
      "numberOfWords": 3,
      "numberOfLetters": 14
    },
    {
      "answer": "Stuart Little",
      "numberOfWords": 2,
      "numberOfLetters": 12
    },
    {
      "answer": "Sunday In The Park With George",
      "numberOfWords": 6,
      "numberOfLetters": 25
    },
    {
      "answer": "Sunset In Venice",
      "numberOfWords": 3,
      "numberOfLetters": 14
    },
    {
      "answer": "Swan Lake",
      "numberOfWords": 2,
      "numberOfLetters": 8
    },
    {
      "answer": "Sweeney Todd The Demon Barber Of Fleet Street",
      "numberOfWords": 8,
      "numberOfLetters": 38
    },
    {
      "answer": "Sweet Smell Of Success",
      "numberOfWords": 4,
      "numberOfLetters": 19
    },
    {
      "answer": "Sycamore Row",
      "numberOfWords": 2,
      "numberOfLetters": 11
    },
    {
      "answer": "Sylvester And The Magic Pebble",
      "numberOfWords": 5,
      "numberOfLetters": 26
    },
    {
      "answer": "Taste Of Home",
      "numberOfWords": 3,
      "numberOfLetters": 11
    },
    {
      "answer": "Ten Apples Up On Top",
      "numberOfWords": 5,
      "numberOfLetters": 16
    },
    {
      "answer": "Tender Is The Night",
      "numberOfWords": 4,
      "numberOfLetters": 16
    },
    {
      "answer": "The Accidental Time Machine",
      "numberOfWords": 4,
      "numberOfLetters": 24
    },
    {
      "answer": "The Addams Family",
      "numberOfWords": 3,
      "numberOfLetters": 15
    },
    {
      "answer": "The Adventures Of Tom Sawyer",
      "numberOfWords": 5,
      "numberOfLetters": 24
    },
    {
      "answer": "The Age Of Innocence",
      "numberOfWords": 4,
      "numberOfLetters": 17
    },
    {
      "answer": "The Alchemist",
      "numberOfWords": 2,
      "numberOfLetters": 12
    },
    {
      "answer": "The Ant And The Grasshopper",
      "numberOfWords": 5,
      "numberOfLetters": 23
    },
    {
      "answer": "The Apple Dumpling Gang",
      "numberOfWords": 4,
      "numberOfLetters": 20
    },
    {
      "answer": "The Archies",
      "numberOfWords": 2,
      "numberOfLetters": 10
    },
    {
      "answer": "The Archies",
      "numberOfWords": 2,
      "numberOfLetters": 10
    },
    {
      "answer": "The Arizona Republic",
      "numberOfWords": 3,
      "numberOfLetters": 18
    },
    {
      "answer": "The Art Of Travel",
      "numberOfWords": 4,
      "numberOfLetters": 14
    },
    {
      "answer": "The Aspern Papers",
      "numberOfWords": 3,
      "numberOfLetters": 15
    },
    {
      "answer": "The Atlantic",
      "numberOfWords": 2,
      "numberOfLetters": 11
    },
    {
      "answer": "The Avengers",
      "numberOfWords": 2,
      "numberOfLetters": 11
    },
    {
      "answer": "The Beach",
      "numberOfWords": 2,
      "numberOfLetters": 8
    },
    {
      "answer": "The Bean Trees",
      "numberOfWords": 3,
      "numberOfLetters": 12
    },
    {
      "answer": "The Bear And The Bees",
      "numberOfWords": 5,
      "numberOfLetters": 17
    },
    {
      "answer": "The Bear And The Dragon",
      "numberOfWords": 5,
      "numberOfLetters": 19
    },
    {
      "answer": "The Beautiful Bureaucrat",
      "numberOfWords": 3,
      "numberOfLetters": 22
    },
    {
      "answer": "The Bill Of Rights",
      "numberOfWords": 4,
      "numberOfLetters": 15
    },
    {
      "answer": "The Black Dahlia",
      "numberOfWords": 3,
      "numberOfLetters": 14
    },
    {
      "answer": "The Black Stallion",
      "numberOfWords": 3,
      "numberOfLetters": 16
    },
    {
      "answer": "The Blood Of Olympus",
      "numberOfWords": 4,
      "numberOfLetters": 17
    },
    {
      "answer": "The Blue Lotus",
      "numberOfWords": 3,
      "numberOfLetters": 12
    },
    {
      "answer": "The Bone Bridge A Brothers Story",
      "numberOfWords": 6,
      "numberOfLetters": 27
    },
    {
      "answer": "The Book Of Life",
      "numberOfWords": 4,
      "numberOfLetters": 13
    },
    {
      "answer": "The Book Of Strange New Things",
      "numberOfWords": 6,
      "numberOfLetters": 25
    },
    {
      "answer": "The Book Thief",
      "numberOfWords": 3,
      "numberOfLetters": 12
    },
    {
      "answer": "The Boy From Oz",
      "numberOfWords": 4,
      "numberOfLetters": 12
    },
    {
      "answer": "The Boy Who Cried Wolf",
      "numberOfWords": 5,
      "numberOfLetters": 18
    },
    {
      "answer": "The Call Of The Wild",
      "numberOfWords": 5,
      "numberOfLetters": 16
    },
    {
      "answer": "The CanCan",
      "numberOfWords": 2,
      "numberOfLetters": 9
    },
    {
      "answer": "The Canterbury Tales",
      "numberOfWords": 3,
      "numberOfLetters": 18
    },
    {
      "answer": "The Cat In The Hat",
      "numberOfWords": 5,
      "numberOfLetters": 14
    },
    {
      "answer": "The Cat In The Hat I Can Do That",
      "numberOfWords": 9,
      "numberOfLetters": 24
    },
    {
      "answer": "The Chocolate War",
      "numberOfWords": 3,
      "numberOfLetters": 15
    },
    {
      "answer": "The Chronicles Of Narnia",
      "numberOfWords": 4,
      "numberOfLetters": 21
    },
    {
      "answer": "The Clan Of The Cave Bear",
      "numberOfWords": 6,
      "numberOfLetters": 20
    },
    {
      "answer": "The Color Of Money",
      "numberOfWords": 4,
      "numberOfLetters": 15
    },
    {
      "answer": "The Color Purple",
      "numberOfWords": 3,
      "numberOfLetters": 14
    },
    {
      "answer": "The Comedy Of Errors",
      "numberOfWords": 4,
      "numberOfLetters": 17
    },
    {
      "answer": "The Confessions Of Noa Weber",
      "numberOfWords": 5,
      "numberOfLetters": 24
    },
    {
      "answer": "The Constitution Of The United States",
      "numberOfWords": 6,
      "numberOfLetters": 32
    },
    {
      "answer": "The Corrections",
      "numberOfWords": 2,
      "numberOfLetters": 14
    },
    {
      "answer": "The Count Of Monte Cristo",
      "numberOfWords": 5,
      "numberOfLetters": 21
    },
    {
      "answer": "The Country Of Ice Cream Star",
      "numberOfWords": 6,
      "numberOfLetters": 24
    },
    {
      "answer": "The Creation Of Adam",
      "numberOfWords": 4,
      "numberOfLetters": 17
    },
    {
      "answer": "The Cricket In Times Square",
      "numberOfWords": 5,
      "numberOfLetters": 23
    },
    {
      "answer": "The Da Vince Code",
      "numberOfWords": 4,
      "numberOfLetters": 14
    },
    {
      "answer": "The Da Vinci Code",
      "numberOfWords": 4,
      "numberOfLetters": 14
    },
    {
      "answer": "The Dark Knight",
      "numberOfWords": 3,
      "numberOfLetters": 13
    },
    {
      "answer": "The Day The Crayons Come Home",
      "numberOfWords": 6,
      "numberOfLetters": 24
    },
    {
      "answer": "The Day The Crayons Quit",
      "numberOfWords": 5,
      "numberOfLetters": 20
    },
    {
      "answer": "The Declaration Of Independence",
      "numberOfWords": 4,
      "numberOfLetters": 28
    },
    {
      "answer": "The Denver Post",
      "numberOfWords": 3,
      "numberOfLetters": 13
    },
    {
      "answer": "The Devil Wears Prada",
      "numberOfWords": 4,
      "numberOfLetters": 18
    },
    {
      "answer": "The Emperors New Clothes",
      "numberOfWords": 4,
      "numberOfLetters": 21
    },
    {
      "answer": "The Excellent Lombards",
      "numberOfWords": 3,
      "numberOfLetters": 20
    },
    {
      "answer": "The Fallback Plan",
      "numberOfWords": 3,
      "numberOfLetters": 15
    },
    {
      "answer": "The Family Circus",
      "numberOfWords": 3,
      "numberOfLetters": 15
    },
    {
      "answer": "The Far Side",
      "numberOfWords": 3,
      "numberOfLetters": 10
    },
    {
      "answer": "The Farmer In The Dell",
      "numberOfWords": 5,
      "numberOfLetters": 18
    },
    {
      "answer": "The Fault In Our Stars",
      "numberOfWords": 5,
      "numberOfLetters": 18
    },
    {
      "answer": "The Federalist Papers",
      "numberOfWords": 3,
      "numberOfLetters": 19
    },
    {
      "answer": "The Feminine Mystique",
      "numberOfWords": 3,
      "numberOfLetters": 19
    },
    {
      "answer": "The First Snow",
      "numberOfWords": 3,
      "numberOfLetters": 12
    },
    {
      "answer": "The Fox  The Pheasants",
      "numberOfWords": 4,
      "numberOfLetters": 18
    },
    {
      "answer": "The Fox And The Pheasants",
      "numberOfWords": 5,
      "numberOfLetters": 21
    },
    {
      "answer": "The Frog And The Mouse",
      "numberOfWords": 5,
      "numberOfLetters": 18
    },
    {
      "answer": "The Frog Prince",
      "numberOfWords": 3,
      "numberOfLetters": 13
    },
    {
      "answer": "The Fundamental Orders",
      "numberOfWords": 3,
      "numberOfLetters": 20
    },
    {
      "answer": "The Game Of Life",
      "numberOfWords": 4,
      "numberOfLetters": 13
    },
    {
      "answer": "The Gift Of The Magi",
      "numberOfWords": 5,
      "numberOfLetters": 16
    },
    {
      "answer": "The Girl From Everywhere",
      "numberOfWords": 4,
      "numberOfLetters": 21
    },
    {
      "answer": "The Girl In The Spiders Web",
      "numberOfWords": 6,
      "numberOfLetters": 22
    },
    {
      "answer": "The Girl Who Kicked The Hornets Nest",
      "numberOfWords": 7,
      "numberOfLetters": 30
    },
    {
      "answer": "The Girl With The Dragon Tattoo",
      "numberOfWords": 6,
      "numberOfLetters": 26
    },
    {
      "answer": "The Giving Tree",
      "numberOfWords": 3,
      "numberOfLetters": 13
    },
    {
      "answer": "The Glass Menagerie",
      "numberOfWords": 3,
      "numberOfLetters": 17
    },
    {
      "answer": "The Gnat And The Bull",
      "numberOfWords": 5,
      "numberOfLetters": 17
    },
    {
      "answer": "The Godfather",
      "numberOfWords": 2,
      "numberOfLetters": 12
    },
    {
      "answer": "The Golden Bird",
      "numberOfWords": 3,
      "numberOfLetters": 13
    },
    {
      "answer": "The Golden Compass",
      "numberOfWords": 3,
      "numberOfLetters": 16
    },
    {
      "answer": "The Golden Goose",
      "numberOfWords": 3,
      "numberOfLetters": 14
    },
    {
      "answer": "The Goonies",
      "numberOfWords": 2,
      "numberOfLetters": 10
    },
    {
      "answer": "The Goose That Laid The Golden Egg",
      "numberOfWords": 7,
      "numberOfLetters": 28
    },
    {
      "answer": "The Goose That Laid The Golden Eggs",
      "numberOfWords": 7,
      "numberOfLetters": 29
    },
    {
      "answer": "The Gourmet Cookbook",
      "numberOfWords": 3,
      "numberOfLetters": 18
    },
    {
      "answer": "The Grapes Of Wrath",
      "numberOfWords": 4,
      "numberOfLetters": 16
    },
    {
      "answer": "The Greatest Show On Earth",
      "numberOfWords": 5,
      "numberOfLetters": 22
    },
    {
      "answer": "The Grinch Who Stole Christmas",
      "numberOfWords": 5,
      "numberOfLetters": 26
    },
    {
      "answer": "The Guggenheim Collection",
      "numberOfWords": 3,
      "numberOfLetters": 23
    },
    {
      "answer": "The Haunting",
      "numberOfWords": 2,
      "numberOfLetters": 11
    },
    {
      "answer": "The Heart Of A Woman",
      "numberOfWords": 5,
      "numberOfLetters": 16
    },
    {
      "answer": "The Heartland Of Europe",
      "numberOfWords": 4,
      "numberOfLetters": 20
    },
    {
      "answer": "The Hobbit",
      "numberOfWords": 2,
      "numberOfLetters": 9
    },
    {
      "answer": "The Hollywood Reporter",
      "numberOfWords": 3,
      "numberOfLetters": 20
    },
    {
      "answer": "The Hunchback Of NorteDame",
      "numberOfWords": 4,
      "numberOfLetters": 23
    },
    {
      "answer": "The Hunchback Of NotreDame",
      "numberOfWords": 4,
      "numberOfLetters": 23
    },
    {
      "answer": "The Hundred Secret Senses",
      "numberOfWords": 4,
      "numberOfLetters": 22
    },
    {
      "answer": "The Hunger Games",
      "numberOfWords": 3,
      "numberOfLetters": 14
    },
    {
      "answer": "The Hunt For Red October",
      "numberOfWords": 5,
      "numberOfLetters": 20
    },
    {
      "answer": "The Husbands Secret",
      "numberOfWords": 3,
      "numberOfLetters": 17
    },
    {
      "answer": "The Importance Of Being Earnest",
      "numberOfWords": 5,
      "numberOfLetters": 27
    },
    {
      "answer": "The Invention Of Wings",
      "numberOfWords": 4,
      "numberOfLetters": 19
    },
    {
      "answer": "The Jungle Book",
      "numberOfWords": 3,
      "numberOfLetters": 13
    },
    {
      "answer": "The Kid And The Wolf",
      "numberOfWords": 5,
      "numberOfLetters": 16
    },
    {
      "answer": "The King Of Queens",
      "numberOfWords": 4,
      "numberOfLetters": 15
    },
    {
      "answer": "The Kite Runner",
      "numberOfWords": 3,
      "numberOfLetters": 13
    },
    {
      "answer": "The Lady And The Unicorn",
      "numberOfWords": 5,
      "numberOfLetters": 20
    },
    {
      "answer": "The Land Of Painted Caves",
      "numberOfWords": 5,
      "numberOfLetters": 21
    },
    {
      "answer": "The Land That Time Forgot",
      "numberOfWords": 5,
      "numberOfLetters": 21
    },
    {
      "answer": "The Last Days On Mars",
      "numberOfWords": 5,
      "numberOfLetters": 17
    },
    {
      "answer": "The Last Precinct",
      "numberOfWords": 3,
      "numberOfLetters": 15
    },
    {
      "answer": "The Legend Of Sleepy Hollow",
      "numberOfWords": 5,
      "numberOfLetters": 23
    },
    {
      "answer": "The Library Of Babel",
      "numberOfWords": 4,
      "numberOfLetters": 17
    },
    {
      "answer": "The Lightning Thief",
      "numberOfWords": 3,
      "numberOfLetters": 17
    },
    {
      "answer": "The Lion King",
      "numberOfWords": 3,
      "numberOfLetters": 11
    },
    {
      "answer": "The Lion The Witch And The Wardrobe",
      "numberOfWords": 7,
      "numberOfLetters": 29
    },
    {
      "answer": "The Lion The Witch And The Wardrobe",
      "numberOfWords": 7,
      "numberOfLetters": 29
    },
    {
      "answer": "The Little Engine That Could",
      "numberOfWords": 5,
      "numberOfLetters": 24
    },
    {
      "answer": "The Little Golden Bird",
      "numberOfWords": 4,
      "numberOfLetters": 19
    },
    {
      "answer": "The Little Match Girl",
      "numberOfWords": 4,
      "numberOfLetters": 18
    },
    {
      "answer": "The Little Paris Bookshop",
      "numberOfWords": 4,
      "numberOfLetters": 22
    },
    {
      "answer": "The Lorax",
      "numberOfWords": 2,
      "numberOfLetters": 8
    },
    {
      "answer": "The Lord Of The Rings",
      "numberOfWords": 5,
      "numberOfLetters": 17
    },
    {
      "answer": "The Lord Of The Rings The Two Towers",
      "numberOfWords": 8,
      "numberOfLetters": 29
    },
    {
      "answer": "The Los Angeles Times Bestseller",
      "numberOfWords": 5,
      "numberOfLetters": 28
    },
    {
      "answer": "The Lost World",
      "numberOfWords": 3,
      "numberOfLetters": 12
    },
    {
      "answer": "The Magic Fiddle",
      "numberOfWords": 3,
      "numberOfLetters": 14
    },
    {
      "answer": "The Magicians Assistant",
      "numberOfWords": 3,
      "numberOfLetters": 21
    },
    {
      "answer": "The Mammoth Hunters",
      "numberOfWords": 3,
      "numberOfLetters": 17
    },
    {
      "answer": "The Man In The Moon",
      "numberOfWords": 5,
      "numberOfLetters": 15
    },
    {
      "answer": "The Manchurian Candidate",
      "numberOfWords": 3,
      "numberOfLetters": 22
    },
    {
      "answer": "The Marriage Of Figaro",
      "numberOfWords": 4,
      "numberOfLetters": 19
    },
    {
      "answer": "The Marriage Of Opposites",
      "numberOfWords": 4,
      "numberOfLetters": 22
    },
    {
      "answer": "The Martian",
      "numberOfWords": 2,
      "numberOfLetters": 10
    },
    {
      "answer": "The Merchant Of Venice",
      "numberOfWords": 4,
      "numberOfLetters": 19
    },
    {
      "answer": "The Miami Herald",
      "numberOfWords": 3,
      "numberOfLetters": 14
    },
    {
      "answer": "The Mosquito Coast",
      "numberOfWords": 3,
      "numberOfLetters": 16
    },
    {
      "answer": "The Most Happy Fella",
      "numberOfWords": 4,
      "numberOfLetters": 17
    },
    {
      "answer": "The Moth Radio Hour",
      "numberOfWords": 4,
      "numberOfLetters": 16
    },
    {
      "answer": "The Mouse That Roared",
      "numberOfWords": 4,
      "numberOfLetters": 18
    },
    {
      "answer": "The Music Man",
      "numberOfWords": 3,
      "numberOfLetters": 11
    },
    {
      "answer": "The Myth Of Halcyon",
      "numberOfWords": 4,
      "numberOfLetters": 16
    },
    {
      "answer": "The Myth Of Hera And Persephone",
      "numberOfWords": 6,
      "numberOfLetters": 26
    },
    {
      "answer": "The Name Of Rose",
      "numberOfWords": 4,
      "numberOfLetters": 13
    },
    {
      "answer": "The Name Of The Rose",
      "numberOfWords": 5,
      "numberOfLetters": 16
    },
    {
      "answer": "The Namesake",
      "numberOfWords": 2,
      "numberOfLetters": 11
    },
    {
      "answer": "The New York Times",
      "numberOfWords": 4,
      "numberOfLetters": 15
    },
    {
      "answer": "The New York Times Sunday Book Review",
      "numberOfWords": 7,
      "numberOfLetters": 31
    },
    {
      "answer": "The New Yorker",
      "numberOfWords": 3,
      "numberOfLetters": 12
    },
    {
      "answer": "The Night Circus",
      "numberOfWords": 3,
      "numberOfLetters": 14
    },
    {
      "answer": "The Nightingale",
      "numberOfWords": 2,
      "numberOfLetters": 14
    },
    {
      "answer": "The Nine Tailors",
      "numberOfWords": 3,
      "numberOfLetters": 14
    },
    {
      "answer": "The North Wind And The Sun",
      "numberOfWords": 6,
      "numberOfLetters": 21
    },
    {
      "answer": "The Nutcracker",
      "numberOfWords": 2,
      "numberOfLetters": 13
    },
    {
      "answer": "The Osullivan Twins",
      "numberOfWords": 3,
      "numberOfLetters": 17
    },
    {
      "answer": "The Once And Future King",
      "numberOfWords": 5,
      "numberOfLetters": 20
    },
    {
      "answer": "The Only Ones",
      "numberOfWords": 3,
      "numberOfLetters": 11
    },
    {
      "answer": "The Owl And The Grasshopper",
      "numberOfWords": 5,
      "numberOfLetters": 23
    },
    {
      "answer": "The Owl And The Pussycat",
      "numberOfWords": 5,
      "numberOfLetters": 20
    },
    {
      "answer": "The Oxford English Dictionary",
      "numberOfWords": 4,
      "numberOfLetters": 26
    },
    {
      "answer": "The Pale Blue Eye",
      "numberOfWords": 4,
      "numberOfLetters": 14
    },
    {
      "answer": "The Pelican Brief",
      "numberOfWords": 3,
      "numberOfLetters": 15
    },
    {
      "answer": "The Perfect Storm",
      "numberOfWords": 3,
      "numberOfLetters": 15
    },
    {
      "answer": "The Phantom Of The Opera",
      "numberOfWords": 5,
      "numberOfLetters": 20
    },
    {
      "answer": "The Pied Piper Of Hamelin",
      "numberOfWords": 5,
      "numberOfLetters": 21
    },
    {
      "answer": "The Pledge Of Allegiance",
      "numberOfWords": 4,
      "numberOfLetters": 21
    },
    {
      "answer": "The Polar Express",
      "numberOfWords": 3,
      "numberOfLetters": 15
    },
    {
      "answer": "The Portrait Of A Lady",
      "numberOfWords": 5,
      "numberOfLetters": 18
    },
    {
      "answer": "The Price Is Right",
      "numberOfWords": 4,
      "numberOfLetters": 15
    },
    {
      "answer": "The Prince And The Pauper",
      "numberOfWords": 5,
      "numberOfLetters": 21
    },
    {
      "answer": "The Princess Diaries",
      "numberOfWords": 3,
      "numberOfLetters": 18
    },
    {
      "answer": "The Princeton Review",
      "numberOfWords": 3,
      "numberOfLetters": 18
    },
    {
      "answer": "The Producers",
      "numberOfWords": 2,
      "numberOfLetters": 12
    },
    {
      "answer": "The Red Pony",
      "numberOfWords": 3,
      "numberOfLetters": 10
    },
    {
      "answer": "The Ren  Stimpy Show",
      "numberOfWords": 4,
      "numberOfLetters": 16
    },
    {
      "answer": "The Return Of The King",
      "numberOfWords": 5,
      "numberOfLetters": 18
    },
    {
      "answer": "The Rocky Horror Show",
      "numberOfWords": 4,
      "numberOfLetters": 18
    },
    {
      "answer": "The Rosetta Stone",
      "numberOfWords": 3,
      "numberOfLetters": 15
    },
    {
      "answer": "The Rosie Project",
      "numberOfWords": 3,
      "numberOfLetters": 15
    },
    {
      "answer": "The Scarlet Letter",
      "numberOfWords": 3,
      "numberOfLetters": 16
    },
    {
      "answer": "The Seattle Times",
      "numberOfWords": 3,
      "numberOfLetters": 15
    },
    {
      "answer": "The Secret Garden",
      "numberOfWords": 3,
      "numberOfLetters": 15
    },
    {
      "answer": "The Secret Life Of Plants",
      "numberOfWords": 5,
      "numberOfLetters": 21
    },
    {
      "answer": "The Settlers Of Catan",
      "numberOfWords": 4,
      "numberOfLetters": 18
    },
    {
      "answer": "The Shadow Queen",
      "numberOfWords": 3,
      "numberOfLetters": 14
    },
    {
      "answer": "The Shape Of Things To Come",
      "numberOfWords": 6,
      "numberOfLetters": 22
    },
    {
      "answer": "The Show Must Go On",
      "numberOfWords": 5,
      "numberOfLetters": 15
    },
    {
      "answer": "The Silver Chair",
      "numberOfWords": 3,
      "numberOfLetters": 14
    },
    {
      "answer": "The Sirens Of Titan",
      "numberOfWords": 4,
      "numberOfLetters": 16
    },
    {
      "answer": "The Sneaky Snacky Squirrel Game",
      "numberOfWords": 5,
      "numberOfLetters": 27
    },
    {
      "answer": "The Snowy Day",
      "numberOfWords": 3,
      "numberOfLetters": 11
    },
    {
      "answer": "The Song Of Roland",
      "numberOfWords": 4,
      "numberOfLetters": 15
    },
    {
      "answer": "The Sound And The Fury",
      "numberOfWords": 5,
      "numberOfLetters": 18
    },
    {
      "answer": "The Sound Of Music",
      "numberOfWords": 4,
      "numberOfLetters": 15
    },
    {
      "answer": "The Sounds Of Seabirds",
      "numberOfWords": 4,
      "numberOfLetters": 19
    },
    {
      "answer": "The Star Side Of Bird Hill",
      "numberOfWords": 6,
      "numberOfLetters": 21
    },
    {
      "answer": "The Starship Enterprise",
      "numberOfWords": 3,
      "numberOfLetters": 21
    },
    {
      "answer": "The Story Of The Lost Child",
      "numberOfWords": 6,
      "numberOfLetters": 22
    },
    {
      "answer": "The Story Of The Snow Children",
      "numberOfWords": 6,
      "numberOfLetters": 25
    },
    {
      "answer": "The Summer Remains",
      "numberOfWords": 3,
      "numberOfLetters": 16
    },
    {
      "answer": "The Sun Also Rises",
      "numberOfWords": 4,
      "numberOfLetters": 15
    },
    {
      "answer": "The Sunlit Night",
      "numberOfWords": 3,
      "numberOfLetters": 14
    },
    {
      "answer": "The Swans Of Fifth Avenue",
      "numberOfWords": 5,
      "numberOfLetters": 21
    },
    {
      "answer": "The Swiss Family Robinson",
      "numberOfWords": 4,
      "numberOfLetters": 22
    },
    {
      "answer": "The Sydney Morning Herald",
      "numberOfWords": 4,
      "numberOfLetters": 22
    },
    {
      "answer": "The Taming Of The Shrew",
      "numberOfWords": 5,
      "numberOfLetters": 19
    },
    {
      "answer": "The TellTale Heart",
      "numberOfWords": 3,
      "numberOfLetters": 16
    },
    {
      "answer": "The Tennessean",
      "numberOfWords": 2,
      "numberOfLetters": 13
    },
    {
      "answer": "The Thin Place",
      "numberOfWords": 3,
      "numberOfLetters": 12
    },
    {
      "answer": "The Three Little Pigs",
      "numberOfWords": 4,
      "numberOfLetters": 18
    },
    {
      "answer": "The Three Musketeers",
      "numberOfWords": 3,
      "numberOfLetters": 18
    },
    {
      "answer": "The Threepenny Opera",
      "numberOfWords": 3,
      "numberOfLetters": 18
    },
    {
      "answer": "The Time Machine",
      "numberOfWords": 3,
      "numberOfLetters": 14
    },
    {
      "answer": "The Time Travelers Wife",
      "numberOfWords": 4,
      "numberOfLetters": 20
    },
    {
      "answer": "The Trouble With Tribbles",
      "numberOfWords": 4,
      "numberOfLetters": 22
    },
    {
      "answer": "The Turner House",
      "numberOfWords": 3,
      "numberOfLetters": 14
    },
    {
      "answer": "The Twelve Huntsmen",
      "numberOfWords": 3,
      "numberOfLetters": 17
    },
    {
      "answer": "The Twelve Tribes Of Hattie",
      "numberOfWords": 5,
      "numberOfLetters": 23
    },
    {
      "answer": "The TwentyOne Balloons",
      "numberOfWords": 3,
      "numberOfLetters": 20
    },
    {
      "answer": "The Ugly Duckling",
      "numberOfWords": 3,
      "numberOfLetters": 15
    },
    {
      "answer": "The Vampire Chronicles",
      "numberOfWords": 3,
      "numberOfLetters": 20
    },
    {
      "answer": "The Vampire Lestat",
      "numberOfWords": 3,
      "numberOfLetters": 16
    },
    {
      "answer": "The Velveteen Rabbit",
      "numberOfWords": 3,
      "numberOfLetters": 18
    },
    {
      "answer": "The Very Hungry Caterpillar",
      "numberOfWords": 4,
      "numberOfLetters": 24
    },
    {
      "answer": "The Walrus And The Carpenter",
      "numberOfWords": 5,
      "numberOfLetters": 24
    },
    {
      "answer": "The Washington Times",
      "numberOfWords": 3,
      "numberOfLetters": 18
    },
    {
      "answer": "The Whos Tommy",
      "numberOfWords": 3,
      "numberOfLetters": 12
    },
    {
      "answer": "The Wild Robot",
      "numberOfWords": 3,
      "numberOfLetters": 12
    },
    {
      "answer": "The WindUp Bird Chronicle",
      "numberOfWords": 4,
      "numberOfLetters": 22
    },
    {
      "answer": "The Wizard Of Oz",
      "numberOfWords": 4,
      "numberOfLetters": 13
    },
    {
      "answer": "The Wonderful Wizard Of Oz",
      "numberOfWords": 5,
      "numberOfLetters": 22
    },
    {
      "answer": "The World Almanac For Kids",
      "numberOfWords": 5,
      "numberOfLetters": 22
    },
    {
      "answer": "The World Factbook",
      "numberOfWords": 3,
      "numberOfLetters": 16
    },
    {
      "answer": "There Was A Crooked Man",
      "numberOfWords": 5,
      "numberOfLetters": 19
    },
    {
      "answer": "Things Fall Apart",
      "numberOfWords": 3,
      "numberOfLetters": 15
    },
    {
      "answer": "Things Mother Taught Me",
      "numberOfWords": 4,
      "numberOfLetters": 20
    },
    {
      "answer": "This Side Of Paradise",
      "numberOfWords": 4,
      "numberOfLetters": 18
    },
    {
      "answer": "Three Billy Goats Gruff",
      "numberOfWords": 4,
      "numberOfLetters": 20
    },
    {
      "answer": "Through The Looking Glass",
      "numberOfWords": 4,
      "numberOfLetters": 22
    },
    {
      "answer": "Thumbelina",
      "numberOfWords": 1,
      "numberOfLetters": 10
    },
    {
      "answer": "Time Magazine",
      "numberOfWords": 2,
      "numberOfLetters": 12
    },
    {
      "answer": "Timeline Discoveries",
      "numberOfWords": 2,
      "numberOfLetters": 19
    },
    {
      "answer": "Timeline Historical Events",
      "numberOfWords": 3,
      "numberOfLetters": 24
    },
    {
      "answer": "Timothy Of The Cay",
      "numberOfWords": 4,
      "numberOfLetters": 15
    },
    {
      "answer": "To Kill A Mockingbird",
      "numberOfWords": 4,
      "numberOfLetters": 18
    },
    {
      "answer": "To Market To Market",
      "numberOfWords": 4,
      "numberOfLetters": 16
    },
    {
      "answer": "Tom Clancy Commander In Chief",
      "numberOfWords": 5,
      "numberOfLetters": 25
    },
    {
      "answer": "TopSecret Files",
      "numberOfWords": 2,
      "numberOfLetters": 14
    },
    {
      "answer": "Touch Of Evil",
      "numberOfWords": 3,
      "numberOfLetters": 11
    },
    {
      "answer": "Town Musicians Of Bremen",
      "numberOfWords": 4,
      "numberOfLetters": 21
    },
    {
      "answer": "Toy Box",
      "numberOfWords": 2,
      "numberOfLetters": 6
    },
    {
      "answer": "Treasure Island",
      "numberOfWords": 2,
      "numberOfLetters": 14
    },
    {
      "answer": "Tv Guide",
      "numberOfWords": 2,
      "numberOfLetters": 7
    },
    {
      "answer": "Twelfth Night",
      "numberOfWords": 2,
      "numberOfLetters": 12
    },
    {
      "answer": "Twenty Thousand Leagues Under The Sea",
      "numberOfWords": 6,
      "numberOfLetters": 32
    },
    {
      "answer": "TwentyThousand Leagues Under The Sea",
      "numberOfWords": 5,
      "numberOfLetters": 32
    },
    {
      "answer": "Twilight Struggle",
      "numberOfWords": 2,
      "numberOfLetters": 16
    },
    {
      "answer": "Twin Peaks",
      "numberOfWords": 2,
      "numberOfLetters": 9
    },
    {
      "answer": "Two Gentlemen Of Verona",
      "numberOfWords": 4,
      "numberOfLetters": 20
    },
    {
      "answer": "US Constitution",
      "numberOfWords": 2,
      "numberOfLetters": 14
    },
    {
      "answer": "Undeveloped Technology",
      "numberOfWords": 2,
      "numberOfLetters": 21
    },
    {
      "answer": "Unfaithful Music  Disappearing Ink",
      "numberOfWords": 4,
      "numberOfLetters": 30
    },
    {
      "answer": "United Kingdoms Daily Mail",
      "numberOfWords": 4,
      "numberOfLetters": 23
    },
    {
      "answer": "United States Constitution",
      "numberOfWords": 3,
      "numberOfLetters": 24
    },
    {
      "answer": "Us Weekly",
      "numberOfWords": 2,
      "numberOfLetters": 8
    },
    {
      "answer": "Usa Today",
      "numberOfWords": 2,
      "numberOfLetters": 8
    },
    {
      "answer": "Value Menu",
      "numberOfWords": 2,
      "numberOfLetters": 9
    },
    {
      "answer": "Vanity Fair",
      "numberOfWords": 2,
      "numberOfLetters": 10
    },
    {
      "answer": "Vermont Life",
      "numberOfWords": 2,
      "numberOfLetters": 11
    },
    {
      "answer": "Veronica Mars",
      "numberOfWords": 2,
      "numberOfLetters": 12
    },
    {
      "answer": "Vivid Imagination",
      "numberOfWords": 2,
      "numberOfLetters": 16
    },
    {
      "answer": "Waiting For Godot",
      "numberOfWords": 3,
      "numberOfLetters": 15
    },
    {
      "answer": "Walk Two Moons",
      "numberOfWords": 3,
      "numberOfLetters": 12
    },
    {
      "answer": "Walking With Dinosaurs",
      "numberOfWords": 3,
      "numberOfLetters": 20
    },
    {
      "answer": "War Of The Worlds",
      "numberOfWords": 4,
      "numberOfLetters": 14
    },
    {
      "answer": "Warm And Kind Demeanor",
      "numberOfWords": 4,
      "numberOfLetters": 19
    },
    {
      "answer": "Washington Crossing The Delaware",
      "numberOfWords": 4,
      "numberOfLetters": 29
    },
    {
      "answer": "Washington Crossing The Deleware",
      "numberOfWords": 4,
      "numberOfLetters": 29
    },
    {
      "answer": "Washington Examiner",
      "numberOfWords": 2,
      "numberOfLetters": 18
    },
    {
      "answer": "Washington Post",
      "numberOfWords": 2,
      "numberOfLetters": 14
    },
    {
      "answer": "Water For Elephants",
      "numberOfWords": 3,
      "numberOfLetters": 17
    },
    {
      "answer": "Watership Down",
      "numberOfWords": 2,
      "numberOfLetters": 13
    },
    {
      "answer": "Websters Dictionary",
      "numberOfWords": 2,
      "numberOfLetters": 18
    },
    {
      "answer": "Wee Willie Winkie",
      "numberOfWords": 3,
      "numberOfLetters": 15
    },
    {
      "answer": "West Side Story",
      "numberOfWords": 3,
      "numberOfLetters": 13
    },
    {
      "answer": "Whats Up Cuz",
      "numberOfWords": 3,
      "numberOfLetters": 10
    },
    {
      "answer": "When Breath Becomes Air",
      "numberOfWords": 4,
      "numberOfLetters": 20
    },
    {
      "answer": "Where The Red Fern Grows",
      "numberOfWords": 5,
      "numberOfLetters": 20
    },
    {
      "answer": "Where The Sidewalk Ends",
      "numberOfWords": 4,
      "numberOfLetters": 20
    },
    {
      "answer": "Where The Wild Things Are",
      "numberOfWords": 5,
      "numberOfLetters": 21
    },
    {
      "answer": "Whistlers Mother",
      "numberOfWords": 2,
      "numberOfLetters": 15
    },
    {
      "answer": "White Fang",
      "numberOfWords": 2,
      "numberOfLetters": 9
    },
    {
      "answer": "Who Loves The Sun",
      "numberOfWords": 4,
      "numberOfLetters": 14
    },
    {
      "answer": "Wicked",
      "numberOfWords": 1,
      "numberOfLetters": 6
    },
    {
      "answer": "Wicked The Musical",
      "numberOfWords": 3,
      "numberOfLetters": 16
    },
    {
      "answer": "Wired Magazine",
      "numberOfWords": 2,
      "numberOfLetters": 13
    },
    {
      "answer": "Wits  Wagers",
      "numberOfWords": 2,
      "numberOfLetters": 10
    },
    {
      "answer": "Woman In A Green Hat",
      "numberOfWords": 5,
      "numberOfLetters": 16
    },
    {
      "answer": "Womans Day",
      "numberOfWords": 2,
      "numberOfLetters": 9
    },
    {
      "answer": "Womens Health Magazine",
      "numberOfWords": 3,
      "numberOfLetters": 20
    },
    {
      "answer": "Womens Wear Daily",
      "numberOfWords": 3,
      "numberOfLetters": 15
    },
    {
      "answer": "Womens Wear Daily",
      "numberOfWords": 3,
      "numberOfLetters": 15
    },
    {
      "answer": "Wooden Didgeridoo",
      "numberOfWords": 2,
      "numberOfLetters": 16
    },
    {
      "answer": "Xia Legends Of A Drift System",
      "numberOfWords": 6,
      "numberOfLetters": 24
    },
    {
      "answer": "Yes Virginia There Is A Santa Claus",
      "numberOfWords": 7,
      "numberOfLetters": 29
    },
    {
      "answer": "Yes Virginia There Is A Santa Clause",
      "numberOfWords": 7,
      "numberOfLetters": 30
    },
    {
      "answer": "You Cant Take It With You",
      "numberOfWords": 6,
      "numberOfLetters": 20
    },
    {
      "answer": "Zen And The Art Of Motorcycle Maintenance",
      "numberOfWords": 7,
      "numberOfLetters": 35
    },
    {
      "answer": "Zen Shorts",
      "numberOfWords": 2,
      "numberOfLetters": 9
    },
    {
      "answer": "Zumanity  Zarkana",
      "numberOfWords": 2,
      "numberOfLetters": 15
    }
  ]
}
